Workbook
Name ZZZ289: Test_Cases!$R$253:$DVH$289

Sheet Project_Info
A1: Project Name:
A2: Client:
A3: Created By:
A4: Creation Date:
A5: Reviewed by:
A6: Type of Testing:

Sheet Requirements
A1: Req_ID | B1: Description | C1: Type | D1: Priority | E1: Status | F1: Version
A2: REQ_LOGIN_01 | B2: System shall allow login with valid email and password | C2: Functional | D2: High | E2: Open
A3: REQ_LOGIN_02 | B3: System shall display warning after 10 minutes of inactivity | C3: Functional | D3: Medium | E3: Open
A4: REQ_LOGIN_03 | B4: System shall reject login with invalid or unregistered email | C4: Functional | D4: High | E4: Open
A5: REQ_LOGIN_04 | B5: System shall reject login with incorrect password | C5: Functional | D5: High | E5: Open
A6: REQ_LOGIN_05 | B6: System shall automatically logout user after inactivity | C6: Functional | D6: High | E6: Open
A7: REQ_LOGIN_06 | B7: System shall support auto login for returning users (Remember Me) | C7: Functional | D7: Medium | E7: Open
A8: REQ_LOGIN_07 | B8: System shall request phone/OTP verification after failed attempts | C8: Security | D8: High | E8: Open
A9: REQ_LOGIN_08 | B9: System shall validate empty email field | C9: Validation | D9: High | E9: Open
A10: REQ_LOGIN_09 | B10: System shall validate empty password field | C10: Validation | D10: High | E10: Open
A11: REQ_LOGIN_10 | B11: System shall treat password as case-sensitive | C11: Functional | D11: High | E11: Open
A12: REQ_LOGIN_11 | B12: System shall lock account after 5 failed login attempts | C12: Security | D12: Critical | E12: Open
A13: REQ_LOGIN_12 | B13: System shall provide "Forgot Password" functionality | C13: Functional | D13: High | E13: Open
... A22: REQ_LOGIN_21 | B22: System shall handle copy/paste securely in password field | C22: Security | D22: Low | E22: Open

Sheet Project_Plan
A1: Title | B1: Sprint Goal | C1: Plan
A2: Sprint 1 Duration (25/4 - 3/5) | B2: The goal of Sprint 1 is to prepare the complete QA environment, understand the OrangeHRM system, setup Agile tools, create the initial testing documentation, and prepare the project foundation for manual and automation testing. manual: Write User story , test cases, bug report and peer review by Manual team (Edit, Add, Delete) or upload as tickets for login page automation"

Sheet User_Stories
A1: US_ID | B1: UserStory | C1: Acceptance Criteria
B2: No of user stories | C2: =COUNTA(A:A)-1 -> 80
B3: No of Acceptance Criteria | C3: =COUNTA(C$4:C$1048576) -> 1065
A4: ="US_0" & COUNTA($A$1:A1) -> US_01 | B4: As an OrangeHRM user (Admin or ESS), I want to log in using my unique credentials, So that I can securely access my personal dashboard and HR management tools based on my assigned role. | C4: Scenario 1: User Authentication and Login Validation Given the user is on the Login page When the user enters login credentials and clicks the Login button Then the system should authenticate the user according to the provided credentials And When a valid username and password are entered Then the system should redirect the user to the appropriate Dashboard And When an invalid username or password is entered Then the system should deny access And display the generic error message "Invalid credentials" And should not indicate whether the username or password is incorrect And When the password is entered using incorrect letter casing Then the system should reject the login attempt And display the error message "Invalid credentials" And enforce password case sensitivity during authentication.
C5: Scenario 2: Validate Login Page UI Layout Given the user navigates to the Login page When the page loads successfully Then the system should display the required login components Including: Username Field Password Field Login Button OrangeHRM Logo And the Password field should mask entered characters by default And the Login button should be clearly visible and accessible And the OrangeHRM logo should be displayed correctly to maintain brand consistency.
C6: Scenario 3: Validate Login Security Requirements Given the user is on the Login page When the user attempts to log in Then the system should validate all required fields and display "Required" for any empty field(s) And When authentication is successful Then the system should maintain the user session until logout or session timeout And When invalid or malicious input is submitted Then the system should sanitize the input and prevent unauthorized access or security vulnerabilities.
C7: Scenario 4: Validate Login Edge Cases and Accessibility Given the user is on the Login page When five consecutive login attempts fail Then the system should temporarily lock the account for 20 minutes And When the user clicks "Forgot your password?" Then the system should redirect the user to the password reset request page And When the Login page is accessed from mobile, tablet, or desktop devices Then the login form should remain accessible, properly aligned, and fully functional across supported screen sizes.
C8: Scenario 5: Inactivity Warning Given the user is logged into the system, When the user remains inactive for a defined period (e.g., 10 minutes), Then the system should display a warning message indicating inactivity, And the session should remain active until further action or timeout occurs
C9: Scenario 6: Identity Verification After Failed Attempts Given the user enters incorrect login credentials multiple times, When the system detects suspicious or repeated failed attempts, Then the system should require additional identity verification (e.g., redirect to password reset or verification step), And prevent direct login without verification
C10: Scenario 7: Input Trimming Given the user enters username or password with leading or trailing spaces, When the login request is submitted, Then the system should trim unnecessary spaces before validation, And process the credentials correctly
C11: Scenario 8: Username Case Sensitivity Given the user enters the username with different letter cases, When the system processes the login request, Then the username should be treated as case-insensitive, And the user should be able to log in successfully if credentials are valid
C12: Scenario 9: Copy and Paste Behavior in Password Field Given the user is on the login page, When the user performs copy and paste actions in the password field, Then the system should allow paste functionality without breaking login behavior, And authentication should work as expected
C13: Scenario 10: CSRF Token Expiration Handling Given the user is on the login page and the session remains idle for a period of time, When the CSRF token expires and the user submits valid login credentials, Then the system should not block the user with a technical error message, And should display a clear, user-friendly message such as: "Session expired, please refresh the page", And allow the user to retry the login process successfully after refreshing the page
A15: ="US_0" & COUNTA($A$1:A14) -> US_02 | B15: As an OrangeHRM user who cannot remember my password, I want to request a password reset link by providing my username, So that I can securely regain access to my account without exposing my credentials. | C15: Scenario 1: Successful Password Reset Request Given the user is on the "Forgot your password?" page, When they enter a valid, registered username in the system, And they click the "Reset Password" button, Then the system should generate a secure, time-sensitive reset token, And send an email containing the reset link to the email address associated with that username, And redirect the user to a confirmation screen displaying: "Reset password link sent successfully".
C16: Scenario 2: Processing an Invalid Username (Account Harvesting Mitigation) Given the user is on the "Forgot your password?" page, When they enter a username that does not exist in the system, And they click the "Reset Password" button, Then the system should not send an email, And it must display the exact same confirmation screen: "Reset password link sent successfully". Note: This prevents malicious actors from guessing valid usernames based on different system responses
C17: Scenario 3: Input Field Validation Given the user is on the "Forgot your password?" page, When they leave the username field blank, And they click the "Reset Password" button, Then the system must prevent submission, And display a validation error message below the field stating: "Required".
C18: Scenario 4: Canceling the Reset Request Given the user is on the "Forgot your password?" page, When they click the "Cancel" button, Then the system should abort the request without sending an email, And redirect the user back to the primary Login page.
C19: Scenario 5: Rate Limiting on Reset Requests Given the user is on the Forgot Password page, When the same username submits multiple reset requests in a short period, Then the system should rate-limit subsequent requests, And display a message: 'Too many requests. Please try again later. | D19: added new
C20: Scenario 6: Token Expiry Given a password reset email has been sent, When the user clicks the reset link after the token has expired (e.g., after 24h), Then the system should display an error: 'This reset link has expired', And prompt the user to submit a new reset request. | D20: added new
A24: ="US_0" & COUNTA($A$1:A23) -> US_03 | B24: As a Logged-in Admin I want to view, add, search, edit, delete and manage employee records from the PIM page So that I can efficiently maintain accurate and up-to-date employee information within the organization. | C24: Scenario 1: Successful user creation Given I am logged in as Admin When I navigate to Admin → Add User And I fill all required fields correctly And click Save Then the system should create the user successfully And display a success message And the user should appear in the user list
C25: Scenario 2: Required fields validation Given I am on the Add User page When I click Save without filling required fields Then error messages should appear for: User Role Employee Name Username Password Confirm Password
C26: Scenario 3: Password mismatch Given I entered password and confirm password When they are different Then system should show: Passwords do not match
C27: Scenario 4: Username already exists Given I enter an existing username When I try to save Then system should show: Username already exists
C28: Scenario 5: Invalid employee name Given I enter an employee name not in system Then system should show validation error
C29: Scenario 6: Cancel action Given I click Cancel Then I should be redirected to user list page And no data should be saved
A31: ="US_0" & COUNTA($A$1:A30) -> US_04 | B31: As an Admin, I want to view, add, edit, and delete job titles, So that I can manage employee roles and organizational structure effectively. | C31: Scenario 1: View job titles list Given I am logged in as Admin When I navigate to Admin → Job Titles Then I should see a list of job titles And each row should display: Job Title Job Description Note And pagination should be available if needed
C32: Scenario 2: Add new job title Given I am on Job Titles page When I click Add And I enter valid job title details And click Save Then the job title should be added successfully And appear in the list
C33: Scenario 3: Required field validation Given I am adding a new job title When I leave required fields empty Then validation messages should appear
C34: Scenario 4: Edit job title Given I select an existing job title When I update its details And click Save Then changes should be saved successfully And reflected in the list
C35: Scenario 5: Delete job title (single) Given I select a job title When I click Delete And confirm deletion Then the job title should be removed from the list
C36: Scenario 6: Delete multiple job titles Given I select multiple job titles When I click Delete Selected And confirm Then all selected job titles should be deleted
C37: Scenario 7: Cancel delete Given I click delete When I cancel confirmation Then no job title should be deleted
C38: Scenario 8: Search / filter (if available) Given I enter search criteria When I click search Then filtered results should be displayed
C39: Scenario 9: No data case Given there are no job titles Then system should display: No Records Found
A41: ="US_0" & COUNTA($A$1:A40) -> US_05 | B41: As an Admin, I want to create, view, edit, and delete pay grades with salary ranges, So that I can define salary structures for employees in the organization. | C41: Scenario 1: View pay grades list Given I am logged in as Admin When I navigate to Admin → Pay Grades Then I should see a list of pay grades And each row should display: Pay Grade Name And pagination should work correctly
C42: Scenario 2: Add new pay grade Given I am on Pay Grades page When I click Add And I enter a valid pay grade name And click Save Then the pay grade should be created successfully And appear in the list
C43: Scenario 3: Required field validation Given I am adding a new pay grade When I leave the name empty Then the system should display a validation message
C44: Scenario 4: Edit pay grade Given I select an existing pay grade When I update the name And click Save Then the changes should be saved And reflected in the list
C45: Scenario 5: Delete pay grade (single) Given I select a pay grade When I click Delete And confirm Then the pay grade should be removed
C46: Scenario 6: Delete multiple pay grades Given I select multiple pay grades When I click Delete Selected Then all selected pay grades should be deleted
C47: Scenario 7: Cancel delete Given I initiate delete When I cancel Then no pay grade should be removed
C48: Scenario 8: Add salary components (currency + range) Given I open a specific pay grade When I add a salary component with: Currency Minimum Salary Maximum Salary Then the component should be saved successfully And displayed in the salary list
C49: Scenario 9: Salary validation Given I enter salary values When: Minimum > Maximum Negative values Then the system should show validation error
C50: Scenario 10: Multiple currencies Given I add multiple salary components Then each currency should be stored and displayed correctly
C51: Scenario 11: Delete salary component Given I select a salary component When I delete it Then it should be removed
A53: ="US_0" & COUNTA($A$1:A52) -> US_06 | B53: As an Admin, I want to create, edit, and delete employment status types, So that I can categorize employees based on their employment type (e.g., Full-Time, Part-Time, Contract). | C53: Scenario 1: View employment status list Given I am logged in as Admin When I navigate to Admin → Employment Status Then I should see a list of employment statuses And each row should display: Employment Status Name
C54: Scenario 2: Add new employment status Given I am on Employment Status page When I click Add And I enter a valid status name And click Save Then the new status should be created successfully And appear in the list
C55: Scenario 3: Required field validation Given I am adding a new employment status When I leave the field empty Then the system should show a validation error
C56: Scenario 4: Edit employment status Given I select an existing status When I update its name And click Save Then changes should be saved successfully And reflected in the list
C57: Scenario 5: Delete employment status (single) Given I select a status When I click Delete And confirm Then the status should be removed from the list
C58: Scenario 6: Delete multiple employment statuses Given I select multiple statuses When I click Delete Selected Then all selected statuses should be deleted
C59: Scenario 7: Cancel delete Given I initiate deletion When I cancel Then no status should be removed
C60: Scenario 8: Duplicate status name Given I enter an already existing status name When I try to save Then the system should show an error Already exists
C61: Scenario 9: No data case Given there are no employment statuses Then system should display: No Records Found
A63: ="US_0" & COUNTA($A$1:A62) -> US_07 | B63: As an Admin, I want to create, edit, and delete job categories, So that I can organize jobs into meaningful categories (e.g., IT, HR, Finance). | C63: Scenario 1: View job category list Given I am logged in as Admin When I navigate to Admin → Job Categories Then I should see a list of job categories And each row should display: Category Name
C64: Scenario 2: Add new job category Given I am on Job Categories page When I click Add And I enter a valid category name And click Save Then the category should be created successfully And appear in the list
C65: Scenario 3: Required field validation Given I am adding a new category When I leave the field empty Then the system should display a validation error
C66: Scenario 4: Edit job category Given I select an existing category When I update its name And click Save Then the changes should be saved And reflected in the list
C67: Scenario 5: Delete job category (single) Given I select a category When I click Delete And confirm Then the category should be removed
C68: Scenario 6: Delete multiple job categories Given I select multiple categories When I click Delete Selected Then all selected categories should be deleted
C69: Scenario 7: Cancel delete Given I initiate deletion When I cancel Then no category should be removed
C70: Scenario 8: Duplicate category name Given I enter an existing category name When I try to save Then the system should show: Already exists
C71: Scenario 9: No data case Given there are no categories Then the system should display: No Records Found
A73: ="US_0" & COUNTA($A$1:A72) -> US_08 | B73: As an Admin, I want to create, edit, and delete work shifts with working hours and assigned employees, So that I can define and manage employee working schedules effectively. | C73: Scenario 1: View work shift list Given I am logged in as Admin When I navigate to Admin → Work Shifts Then I should see a list of work shifts And each row should display: Shift Name Work Hours (From – To) Assigned Employees
C74: Scenario 2: Add new work shift Given I am on Work Shifts page When I click Add And I enter: Shift Name From Time To Time And click Save Then the shift should be created successfully And appear in the list
C75: Scenario 3: Required field validation Given I am creating a shift When required fields are empty Then the system should show validation errors
C76: Scenario 4: Time validation Given I enter shift times When: From Time ≥ To Time Then the system should show an error Invalid time range
C77: Scenario 5: Edit work shift Given I select an existing shift When I update: Name Time And click Save Then changes should be saved successfully
C78: Scenario 6: Assign employees to shift Given I am editing a shift When I assign employees Then they should be linked to the shift And displayed in the shift details
C79: Scenario 7: Remove employee from shift Given an employee is assigned When I remove them Then they should no longer be part of the shift
C80: Scenario 8: Delete work shift Given I select a shift When I delete and confirm Then the shift should be removed
C81: Scenario 9: Delete shift with assigned employees Given a shift has assigned employees When I delete it Then system should: Either allow deletion Or show warning (depending on system rules)
C82: Scenario 10: Duplicate shift name Given I enter an existing shift name Then the system should show: Already exists
C83: Scenario 11: No data case Given no work shifts exist Then system should display: No Records Found
A85: ="US_0" & COUNTA($A$1:A84) -> US_09 | B85: As an Admin, I want to view and update the organization’s general information, So that the system reflects accurate company details (name, contact info, registration details, etc.). | C85: Scenario 1: View organization information Given I am logged in as Admin When I navigate to Admin → Organization → General Information Then I should see organization details including: Organization Name Registration Number Tax ID Phone Fax Email Address City / State / Country
C86: Scenario 2: Enable edit mode Given I am on the page When I click Edit Then all editable fields should become enabled
C87: Scenario 3: Update organization information Given I am in edit mode When I update valid data And click Save Then the information should be saved successfully And displayed correctly after saving
C88: Scenario 4: Required field validation Given I am editing information When I leave required fields empty Then the system should show validation errors
C89: Scenario 5: Email validation Given I enter an invalid email format Then the system should show an error Invalid email format
C90: Scenario 6: Phone number validation Given I enter invalid phone number format Then the system should show validation error
C91: Scenario 7: Data persistence Given I update organization data When I refresh the page Then updated data should persist
C92: Scenario 8: Field length validation Given I enter very long values Then system should: either restrict input or show validation error
A94: ="US_" & COUNTA($A$1:A93) -> US_10 | B94: As an Admin, I want to create, view, edit, delete, and search organization locations, So that I can manage company branches and offices with accurate details. | C94: Scenario 1: View locations list Given I am logged in as Admin When I navigate to Admin → Organization → Locations Then I should see a list of locations And each row should display: Name City Country And pagination should work if needed
C95: Scenario 2: Add new location Given I am on Locations page When I click Add And I enter valid details: Name City Country Address (optional fields) And click Save Then the location should be created successfully And appear in the list
C96: Scenario 3: Required field validation Given I am adding a location When required fields (e.g., Name) are empty Then the system should show validation errors
C97: Scenario 4: Edit location Given I select an existing location When I update its details And click Save Then changes should be saved successfully And reflected in the list
C98: Scenario 5: Delete location (single) Given I select a location When I click Delete And confirm Then the location should be removed
C99: Scenario 6: Delete multiple locations Given I select multiple locations When I click Delete Selected Then all selected locations should be deleted
C100: Scenario 7: Cancel delete Given I initiate deletion When I cancel Then no location should be removed
C101: Scenario 8: Search / filter locations Given I enter search criteria (Name, City, Country) When I click Search Then filtered results should be displayed
C102: Scenario 9: Reset search Given I applied filters When I click Reset Then all locations should be displayed again
C103: Scenario 10: Duplicate location name Given I enter an existing location name When I try to save Then the system should show: Already exists
C104: Scenario 11: Country dropdown validation Given I open the country dropdown Then it should: Display available countries Allow selection Save correctly
C105: Scenario 12: No data case Given there are no locations Then the system should display: No Records Found
A107: ="US_" & COUNTA($A$1:A106) -> US_11 | B107: As an Admin, I want to create, edit, and delete organizational units in a hierarchical structure, So that I can represent the company structure (departments, divisions, branches) accurately. | C107: Scenario 1: View organization structure Given I am logged in as Admin When I navigate to Admin → Organization → Structure Then I should see a hierarchical tree of the organization And the root node should represent the company And child nodes should represent departments or units
C108: Scenario 2: Add new organizational unit Given I select a parent node When I click Add And I enter valid details: Unit Name And click Save Then the new unit should be added under the selected parent
C109: Scenario 3: Required field validation Given I am adding a unit When I leave required fields empty Then the system should show validation errors
C110: Scenario 4: Edit organizational unit Given I select an existing unit When I update its name/details And click Save Then changes should be saved successfully
C111: Scenario 5: Delete organizational unit Given I select a unit When I click Delete And confirm Then the unit should be removed from the structure
C112: Scenario 6: Delete unit with children Given a unit has child nodes When I delete it Then system should: either delete all child nodes or show warning (based on system rule)
...

Sheet Test_Cases
A1: TC_ID | B1: Scenario | C1: AC ID | D1: Title | E1: Description | F1: Preconditions | G1: Test Steps | H1: Test Data | I1: Expected Result | J1: Postconditions | K1: Actual Result | L1: Status | M1: Author | N1: Automated | O1: Execution Cycle | P1: Priorty | Q1: Reviewed by | R1: Notes
A2: TC_LOGIN_001 | B2: Login | C2: AC_001 | D2: Verify successful login with valid Username and password | E2: Ensure that the user can log in successfully using valid registered email and password | F2: User is on login page | G2: 1. Enter valid username 2. Enter valid password 3. Click "Login" | H2: username: Admin Password: admin123 | I2: User logs in successfully and is redirected to the dashboard/home page | J2: User session is created and user is logged in | K2: User logged in successfully and redirected to dashboard | L2: Passed | M2: Afram | N2: Yes | O2: v1.0 | P2: Medium
A3: TC_LOGIN_002 | C3: AC_002 | D3: Verify system shows warning message after user inactivity (10 minutes) | E3: Ensure that the system detects user inactivity and displays a warning message after a defined idle time (e.g., 10 minutes) | F3: User is logged in | G3: 1. Login with valid email and password 2. Do not perform any action (no clicks / typing / scrolling) 3. Wait for 10 minutes | H3: username: Admin Password: admin123 | I3: System displays warning message like "You have been inactive for a while" | J3: Session is still active until user takes action | K3: No warning message displayed after 10 minutes | L3: Failed | M3: Afram | N3: Yes | P3: Medium | W3: Team member | X3: Test cases | Y3: Reviewed by
A4: TC_LOGIN_003 | C4: AC_003 | D4: Verify user is automatically logged out after inactivity warning | E4: Ensure system logs out user automatically if no action is taken after warning | F4: Warning message already displayed | G4: 1. Wait for warning message 2. Do not click anything 3. Wait additional 1–2 minutes | H4: username: Admin Password: admin123 | I4: User is automatically logged out and redirected to login page | J4: Session terminated | K4: User remains logged in | L4: Failed | M4: Afram | N4: Yes | P4: Critical | W4: Afram | X4: =COUNTIF(M:M, "Afram") -> 1025 | Y4: =COUNTIF(Q:Q, "Afram") -> 15
A5: TC_LOGIN_004 | C5: AC_004 | D5: Verify system handles expired CSRF token gracefully during login | E5: Ensure that when the CSRF token expires, the system provides a clear message or allows user to recover instead of blocking login abruptly | F5: Page has been idle for a period (token expiration) | G5: 1. Navigate to login page 2. Wait for a period of time (e.g., 5–10 minutes) 3. Enter valid username and password 4. Click "Login" | H5: Username: Admin Password: admin123 | I5: System should either: Allow login successfully, OR Display a user-friendly message like: "Session expired, please refresh the page" | J5: User can recover and proceed with login | K5: System displays "CSRF token validation failed" and blocks login | L5: Failed | M5: Afram | N5: Yes | P5: High | W5: AY | X5: =COUNTIF(M:M, "AY") -> 89 | Y5: =COUNTIF(Q:Q, "AY") -> 18
A6: TC_LOGIN_005 | C6: AC_005 | D6: Verify system requests identity verification after incorrect password attempts using username | E6: Ensure that if the user enters an incorrect password, the system allows the user to verify identity using their username to confirm account ownership | F6: User is registered with a valid username | G6: 1. Enter valid username 2. Enter incorrect password 3. Click "Login" 4. System prompts for identity verification 5. Confirm username / proceed with verification step 6. Submit | H6: Username: Admin Password: wrong123 | I6: System verifies user identity and allows password reset or secure login flow | J6: User proceeds to secure verification or password reset process | K6: System prompted for verification and allowed user to continue | L6: Passed | M6: Afram | N6: Yes | P6: High | W6: Omar | X6: =COUNTIF(M:M, "Omar") -> 310 | Y6: =COUNTIF(Q:Q, "Omar") -> 0
A7: TC_LOGIN_006 | C7: AC_006 | D7: Verify account lockout after 5 failed login attempts | E7: Ensure account is locked after multiple failed attempts | F7: User is registered | G7: 1. Enter valid username 2. Enter wrong password 3. Repeat 5 times 4. Try login again | H7: Username: Admin Password: wrong123 | I7: Account locked for 20 minutes + proper message | J7: User cannot login temporarily | K7: Account not locked | L7: Failed | M7: Afram | N7: Yes | P7: Critical | W7: Aly | X7: =COUNTIF(M:M, "Aly") -> 94 | Y7: =COUNTIF(Q:Q, "Aly") -> 0
A8: TC_LOGIN_007 | C8: AC_007 | D8: Verify "Forgot Password" link redirects correctly | E8: Ensure user can navigate to password reset page | F8: User is registered | G8: 1. Click "Forgot your password? | H8: User redirected to password reset page | I8: User is redirected to the password reset page | J8: Password reset page is displayed and user can initiate reset process | K8: User is successfully redirected to the password reset page | L8: Passed | M8: Afram | N8: Yes | P8: High | W8: Total | X8: =SUM(X4:X7) -> 1518
A9: TC_LOGIN_008 | C9: AC_008 | D9: Verify unauthorized users cannot access dashboard | E9: Ensure restricted pages are not accessible without authentication | F9: User is not logged in | G9: 1. Navigate directly to dashboard URL | H9: N/A | I9: User is redirected to login page | J9: Access is denied | K9: User successfully redirected to login page | L9: Passed | M9: Afram | N9: Yes | P9: Critical
A10: TC_LOGIN_009 | C10: AC_009 | D10: Verify user cannot access dashboard after logout using browser back button | E10: Ensure that after logging out, the user cannot navigate back to the dashboard using the browser back button and must be redirected to the login page | F10: User is on login page | G10: 1. Enter valid username and password 2. Click "Login" 3. Verify user is redirected to Dashboard 4. Click "Logout" 5. Click browser Back button | H10: Username: Admin Password: admin123 | I10: User should be redirected to the login page and not allowed to access the dashboard | J10: Session is terminated and protected pages are inaccessible | K10: User is able to access the dashboard after clicking back | L10: Failed | M10: Afram | N10: Yes | P10: High | W10: EXECUTION OVERVIEW
A11: TC_LOGIN_010 | C11: AC_010 | D11: Verify user cannot access dashboard using Back and Refresh after logout | E11: Ensure that after logout, using browser Back followed by Refresh does not allow access to the dashboard and always redirects to login page | F11: User is on login page | G11: 1. Enter valid username and password 2. Click "Login" 3. Verify user is redirected to Dashboard 4. Click browser Back button without "Logout" 5. Click browser Refresh (F5) | H11: Username: Admin Password: admin123 | I11: User should be redirected to login page and should not access dashboard | J11: Session is terminated and dashboard is inaccessible | K11: User is able to access dashboard after Back and Refresh without logging in | L11: Failed | M11: Afram | P11: High | W11: Test Cases Passed: | X11: =COUNTIF(L:L, "Passed") -> 1343
A12: TC_LOGIN_011 | C12: AC_011 | D12: Verify system prevents SQL injection | E12: Ensure inputs are sanitized against SQL injection | F12: User is on login page | G12: 1. Enter SQL injection payload in username 2. Enter any password 3. Click Login | H12: Username: ' OR 1=1 -- Password: any | I12: Login fails and input is sanitized | J12: System remains secure | K12: user has not logged in | L12: Passed | M12: Afram | P12: Critical | W12: Test Cases Failed: | X12: =COUNTIF(L:L, "Failed") -> 119
A13: TC_LOGIN_012 | C13: AC_012 | D13: Verify copy and paste behavior in password field | E13: Ensure system handles paste actions correctly in password field | F13: User is on login page | G13: 1. Copy password 2. Paste into password field 3. Click "Login" | H13: Username: Admin Password: admin123 | I13: The Password field should not accept the paste action | J13: User is logged in | K13: procedure of copying and pasting was successful | L13: Failed | M13: Afram | N13: Yes | P13: Low | W13: Total Test Cases Executed: | X13: =SUM(X11:X12) -> 1462
A14: TC_LOGIN_013 | C14: AC_013 | D14: Verify password field is masked | E14: Ensure password is hidden While writing | F14: User is on login page | G14: 1. Enter password | H14: Password: 123456 | I14: Password should be hidden (••••••) | J14: Password not visible | K14: Password masked by Eye icon toggle is successfully | L14: Passed | M14: Afram | N14: Yes | P14: High | W14: Automation
A15: TC_LOGIN_014 | C15: AC_014 | D15: Verify session persists after page refresh | E15: Ensure user remains logged in after refreshing the page | F15: User is logged in | G15: 1. Log in successfully 2. Refresh the page | H15: Username: Admin Password: admin123 | I15: User remains logged in | J15: Session remains active | K15: User is logged after refresh | L15: Passed | M15: Afram | N15: Yes | P15: High | W15: Automated | X15: =COUNTIF(N:N, "Yes") -> 710
A16: TC_LOGIN_015 | C16: AC_015 | D16: Verify login page responsiveness across devices | E16: Ensure login page works on mobile/tablet | F16: Open site on different screen sizes | G16: 1. Open on desktop 2. Open on tablet 3. Open on mobile | H16: N/A | I16: Layout adapts correctly on all devices | J16: Usable UI | K16: Layout successfully | L16: Passed | M16: Afram | N16: Yes | P16: High
A17: TC_LOGIN_016 | C17: AC_016 | D17: Verify login page UI elements are displayed correctly | E17: Ensure all required UI components are visible | F17: User is on login page | G17: 1. Check presence of username field 2. Check password field 3. Check login button 4. Check logo | H17: N/A | I17: All UI elements displayed correctly | J17: UI ready for interaction | K17: elements displayed correctly | L17: Passed | M17: Afram | N17: Yes | P17: Medium | W17: Test Case priorties
A18: TC_LOGIN_017 | C18: AC_017 | D18: Verify whether username field is case-sensitive | E18: Ensure system behavior when entering username in different letter cases | F18: User is on login page | G18: 1. Enter username: admin 2. Enter valid password 3. Click "Login" | H18: Username: admin (actual: Admin) Password: admin123 | I18: Login fails (case-sensitive username) | J18: User logged in or access denied based on system behavior | K18: User logged in successfully | L18: Failed | M18: Afram | N18: Yes | P18: High | W18: Critical | X18: =COUNTIF(P:P, "Critical") -> 94
A19: TC_LOGIN_018 | C19: AC_018 | D19: Verify password is case-sensitive | E19: Ensure that login fails when password case is incorrect | F19: User is registered | G19: 1. Enter valid username 2. Enter correct password but with different case 3. Click "Login" | H19: Username: Admin Password: Admin123 (actual: admin123) | I19: Login should fail with "Invalid credentials" | J19: User not logged in | K19: user has not logged in | L19: Passed | M19: Afram | N19: Yes | P19: High | W19: High | X19: =COUNTIF(P:P, "High") -> 722
A20: TC_LOGIN_019 | C20: AC_019 | D20: Verify system trims leading and trailing spaces in input fields | E20: Ensure spaces before and after input values are ignored | F20: User is registered | G20: 1. Enter username with leading and trailing spaces 2. Enter valid password 3. Click "Login" | H20: Username: " Admin " Password: admin123 | I20: Login failed due to spaces | J20: User is logged in | K20: Login CSRF token validation failed | L20: Passed | M20: Afram | N20: Yes | P20: Medium | R20: Delete | W20: Medium | X20: =COUNTIF(P:P, "Medium") -> 460
A21: TC_LOGIN_020 | C21: AC_020 | D21: Verify login fails with invalid username | E21: Ensure that the system does not allow login with an unregistered or invalid username | F21: User is on login page | G21: 1. Enter Invalid email 2. Enter valid password 3. Click "Login" | H21: username: wrong Password: admin123 | I21: Error message "Invalid username or password" is displayed | J21: User is not logged in | K21: User is not logged in | L21: Passed | M21: Afram | N21: Yes | P21: High | W21: Low | X21: =COUNTIF(P:P, "Low") -> 84
A22: TC_LOGIN_021 | C22: AC_021 | D22: Verify login fails with incorrect password | E22: Ensure that the system rejects login when password is incorrect | F22: User is on login page | G22: 1. Enter valid email 2. Enter Wrong password 3. Click "Login" | H22: username: Admin Password: wrong123 | I22: Error message "Invalid username or password" is displayed | J22: User is not logged in | K22: User is not logged in | L22: Passed | M22: Afram | N22: Yes | P22: High
A23: TC_LOGIN_022 | C23: AC_022 | D23: Verify validation when username field is empty | E23: Ensure system shows validation when username is empty | F23: User is on login page | G23: 1. Leave email empty 2. Enter password 3. Click "Login" | H23: username: Password: admin123 | I23: "username is required" message displayed | J23: Login blocked | K23: validation message shown | L23: Passed | M23: Afram | N23: Yes | P23: High
A24: TC_LOGIN_023 | C24: AC_023 | D24: Verify validation when password field is empty | E24: Ensure system shows validation when password is empty | F24: User is on login page | G24: 1. Enter email 2. Leave password empty 3. Click "Login" | H24: username: Admin Password: | I24: "Password is required" message displayed | J24: Login blocked | K24: validation message shown | L24: Passed | M24: Afram | N24: Yes | P24: High
A25: TC_LOGIN_024 | C25: AC_024 | D25: Verify login with Enter key | E25: Ensure user can submit login by pressing Enter | F25: User is on login page | G25: 1. Enter valid username 2. Enter valid password 3. Press Enter key | H25: Username: Admin Password: admin123 | I25: User logs in successfully | J25: User session created | K25: User logged in successfully | L25: Passed | M25: Omar | N25: Yes | P25: Medium | Q25: Afram
A26: TC_LOGIN_025 | C26: AC_025 | D26: Verify login with both fields empty | E26: Ensure validation for both empty fields | F26: User is on login page | G26: 1. Leave username empty 2. Leave password empty 3. Click Login | H26: Username: Password: | I26: "Required" shown under both fields | J26: Login blocked | K26: Required messages shown | L26: Passed | M26: Omar | N26: Yes | P26: High | Q26: Afram
A27: TC_LOGIN_026 | C27: AC_026 | D27: Verify login button is disabled during processing | E27: Ensure double-click prevention during login | F27: User is on login page | G27: 1. Enter valid credentials 2. Click Login rapidly twice | H27: Username: Admin Password: admin123 | I27: Only one login request processed | J27: Single session created | K27: Button allows multiple clicks | L27: Failed | M27: Omar | N27: Yes | P27: Medium | Q27: Afram
A28: TC_LOGIN_027 | C28: AC_027 | D28: Verify password field toggle visibility | E28: Ensure eye icon toggles password visibility | F28: User is on login page | G28: 1. Enter password 2. Click eye icon to show 3. Click again to hide | H28: Password: admin123 | I28: Password toggles between masked and visible | J28: Password display changes | K28: Toggle works correctly | L28: Passed | M28: Omar | N28: Yes | P28: Low | Q28: Afram
A29: TC_LOGIN_028 | C29: AC_028 | D29: Verify footer links and social media icons | E29: Ensure all footer elements are functional | F29: User is on login page | G29: 1. Check copyright text 2. Click OrangeHRM link 3. Click each social media icon | H29: N/A | I29: All links open correct pages in new tabs | J29: Footer elements verified | K29: All links work correctly | L29: Passed | M29: Omar | N29: Yes | P29: Medium | Q29: Afram
A30: TC_LOGIN_029 | C30: AC_031 | D30: Verify login with both fields invalid | E30: Ensure that the user cann't log in successfully using invalid email and password | F30: User is on login page | G30: 1. Enter invalid email 2. Enter invalid password 3. Click "Login" | H30: Email: notadmin Password: wrong123 | I30: login failed | J30: User proceeds to secure verification or password reset process | K30: User failed to log in successfully and redirect to dashboard | L30: Passed | M30: Omar | N30: Yes | P30: High | Q30: Afram
A31: TC_LOGIN_030 | C31: AC_032 | D31: Verfiy double-click login bypass with invalid password | E31: When a user enters a valid username and an incorrect password, clicking the Login button twice in quick succession bypasses authentication and grants access to the dashboard | F31: 1. Browser is open and navigated to the OrangeHRM login page. 2. No user is currently logged in. 3. Login page is fully loaded. | G31: 1. Navigate to https://opensource-demo.orangehrmlive.com/ 2. Enter a valid username in the Username field. 3. Enter an incorrect password in the Password field. 4. Rapidly click the "Login" button two times in quick succession. 5. Observe the application behavior and the page navigated to. | H31: Username: Admin Password: WrongPassword123! | I31: The system should display an "Invalid credentials" error message and remain on the login page. The user should NOT be authenticated or redirected to the Dashboard. | J31: User remains on the login page. No session or authentication token is created. | K31: The system authenticates the user and redirects to the Dashboard page despite the incorrect password being entered. Login is successful after the second click. | L31: Failed | M31: Omar | P31: Critical | Q31: Afram
A32: TC_LOGIN_031 | C32: AC_033 | D32: Login credentials persist in fields after logout | E32: After a user logs out of the application, the login page fields (Username and Password) still retain the previously entered credentials instead of being cleared. This is a security vulnerability as it exposes credentials to the next user of the same browser session. | F32: 1. User is currently logged into the OrangeHRM application with valid credentials. 2. The dashboard or any internal page is displayed. | G32: 1. Login to the application using valid credentials (Username and Password). 2. Verify successful login (Dashboard is displayed). 3. Click on the user profile dropdown in the top-right corner. 4. Click the "Logout" option. 5. Observe the login page after being redirected. 6. Check the Username and Password fields for any pre-filled values. | H32: Username: Admin Password: admin123 | I32: After logout, the login page should be displayed with both the Username and Password fields completely empty/cleared. No previously entered credentials should be visible or pre-filled. | J32: User is redirected to a clean login page with empty Username and Password fields. No session data or cached credentials remain. | K32: After logout, the login page is displayed but the Username and Password fields still contain the previously entered credentials (Admin / admin123). The fields are not cleared upon logout. | L32: Failed | M32: Omar | P32: High | Q32: Afram
A33: TC_LOGIN_032 | D33: Verify login page title is correct in browser tab | E33: Ensure the browser tab displays the correct page title for the login page | F33: User navigates to login page URL | G33: 1. Open https://opensource-demo.orangehrmlive.com/web/index.php/auth/login 2. Check the browser tab title | H33: N/A | I33: Browser tab title should display 'OrangeHRM' | J33: Login page is loaded | K33: Displayed Successfully | L33: Passed | M33: Omar | N33: Yes | P33: Low
A34: TC_LOGIN_033 | D34: Verify login page displays OrangeHRM logo and tagline | E34: Ensure the OrangeHRM logo and tagline 'Wow Factor' are visible on the login page | F34: User is on login page | G34: 1. Navigate to login page 2. Visually inspect logo area 3. Check for tagline text | H34: N/A | I34: OrangeHRM logo and tagline 'Wow Factor' are displayed correctly | J34: Login page loaded | K34: OrangeHRM logo (ohrm_logo.png) and branding image (ohrm_branding.png) are both visible on the login page. | L34: Passed | M34: Omar | N34: Yes | P34: Low
A35: TC_LOGIN_034 | D35: Verify Tab key navigates between Username and Password fields | E35: Ensure keyboard Tab key moves focus from Username to Password to Login button | F35: User is on login page | G35: 1. Click on Username field 2. Press Tab key 3. Observe focus moves to Password 4. Press Tab again 5. Observe focus moves to Login button | H35: N/A | I35: Focus moves: Username → Password → Login button in correct order | J35: Login page loaded | K35: Tab key from Username field correctly moves focus to the Password field (placeholder='Password' confirmed as focused element). | L35: Passed | M35: Omar | N35: Yes | P35: Medium
A36: TC_LOGIN_035 | D36: Verify login with username containing only spaces | E36: Ensure login fails when username contains only whitespace characters | F36: User is on login page | G36: 1. Enter ' ' (spaces only) in username 2. Enter valid password 3. Click Login | H36: Username: ' ' (3 spaces) Password: admin123 | I36: Required' validation message is displayed OR login fails with 'Invalid credentials' | J36: No session created | K36: Login attempt with username containing only spaces (' ') is blocked. 'Required' validation message is displayed. No session created. | L36: Passed | M36: Omar | N36: Yes | P36: Medium
A37: TC_LOGIN_036 | D37: Verify login with password containing only spaces | E37: Ensure login fails when password contains only whitespace characters | F37: User is on login page | G37: 1. Enter 'Admin' in username 2. Enter ' ' (spaces only) in password 3. Click Login | H37: Username: Admin Password: ' ' (3 spaces) | I37: Required' validation message OR 'Invalid credentials' error displayed | J37: No session created | K37: Login attempt with password containing only spaces (' ') is blocked. 'Required' validation message is displayed. No session created. | L37: Passed | M37: Omar | N37: Yes | P37: Medium
A38: TC_LOGIN_037 | D38: Verify login with very long username (boundary test) | E38: Ensure system handles excessively long username input gracefully | F38: User is on login page | G38: 1. Enter 256-character string in username field 2. Enter valid password 3. Click Login | H38: Username: 'A' * 256 Password: admin123 | I38: System either truncates input or displays appropriate validation error. No crash. | J38: No crash or server error | K38: System accepts 256-character username input without truncation. No server crash or 500 error. Login fails with 'Invalid credentials' as expected. | L38: Passed | M38: Omar | N38: Yes | P38: Medium
A39: TC_LOGIN_038 | D39: Verify login with very long password (boundary test) | E39: Ensure system handles excessively long password input gracefully | F39: User is on login page | G39: 1. Enter valid username 2. Enter 256-character string in password field 3. Click Login | H39: Username: Admin Password: 'a' * 256 | I39: System either truncates input or displays 'Invalid credentials'. No crash or server error. | J39: No crash | K39: System accepts 256-character password input without truncation. No server crash or 500 error. Login fails with 'Invalid credentials' as expected. | L39: Passed | M39: Omar | N39: Yes | P39: Medium
A40: TC_LOGIN_039 | D40: Verify password field does not show password in page source | E40: Ensure password input is of type='password' and not exposed in HTML source | F40: User is on login page | G40: 1. Right-click on password field 2. Select Inspect Element 3. Check input type attribute | H40: N/A | I40: Password field input type is 'password', not 'text' | J40: Login page loaded | K40: Password field HTML type attribute = 'password'. Input is correctly masked. Characters are not exposed as plain text. | L40: Passed | M40: Omar | N40: Yes | P40: High
A41: TC_LOGIN_040 | D41: Verify login page is accessible via HTTPS only | E41: Ensure the login page uses HTTPS and HTTP redirects to HTTPS | F41: Browser with network inspection | G41: 1. Open HTTP URL: http://opensource-demo.orangehrmlive.com/web/index.php/auth/login 2. Observe if redirected to HTTPS | H41: N/A | I41: HTTP request is redirected to HTTPS (301/302 redirect). Login page loads only on HTTPS. | J41: Secure connection established | K41: HTTP port 80 is completely blocked (WinError 10061: No connection could be made). The site runs exclusively on HTTPS with no HTTP server active. | L41: Passed | M41: Omar | N41: Yes | P41: High
A42: TC_LOGIN_041 | D42: Verify XSS injection in username field | E42: Ensure system prevents cross-site scripting (XSS) via username input | F42: User is on login page | G42: 1. Enter XSS payload in username: <script>alert('XSS')</script> 2. Enter any password 3. Click Login 4. Observe system behavior | H42: Username: <script>alert('XSS')</script> Password: admin123 | I42: Login fails with 'Invalid credentials'. No script executes. No alert dialog appears. | J42: System remains secure, no script execution | K42: XSS payload '<script>alert(XSS)</script>' entered in username field. No alert dialog triggered. No script executed. Login failed with 'Invalid credentials'. | L42: Passed | M42: Omar | N42: Yes | P42: Critical
A43: TC_LOGIN_042 | D43: Verify login button text is correct | E43: Ensure the login button displays the correct label 'Login' | F43: User is on login page | G43: 1. Navigate to login page 2. Observe the submit button label | H43: N/A | I43: Button displays text 'Login' | J43: Login page loaded | K43: Login submit button label is exactly 'Login'. | L43: Passed | M43: Omar | P43: Low
A44: TC_LOGIN_043 | D44: Verify autocomplete is disabled on password field | E44: Ensure browser autocomplete does not pre-fill the password field | F44: User is on login page using a browser with saved passwords | G44: 1. Navigate to login page 2. Check if password field has autocomplete='off' or 'new-password' 3. Inspect HTML attribute | H44: N/A | I44: Password field has autocomplete='off' or 'new-password' attribute | J44: Login page loaded | K44: Password field autocomplete attribute is NOT set (value = None). The browser may autofill or save passwords without restriction. | L44: Failed | M44: Omar | P44: Medium
A45: TC_LOGIN_044 | D45: Verify login with username containing special characters | E45: Ensure system handles special character usernames gracefully | F45: User is on login page | G45: 1. Enter username with special characters: admin@#$% 2. Enter valid password 3. Click Login | H45: Username: admin@#$% Password: admin123 | I45: System displays 'Invalid credentials' without crashing | J45: No server error | K45: Username with special characters 'admin@#$%' is rejected. 'Invalid credentials' error shown. No server crash, no unexpected dialog. | L45: Passed | M45: Omar | N45: Yes | P45: Medium
A46: TC_LOGIN_045 | D46: Verify that username field placeholder text is visible | E46: Ensure the username field displays placeholder text 'Username' | F46: User is on login page | G46: 1. Navigate to login page 2. Observe the username field without clicking | H46: N/A | I46: Username field displays placeholder text 'Username' | J46: Login page loaded | K46: Username input field displays placeholder text 'Username' when empty. | L46: Passed | M46: Omar | N46: Yes | P46: Low
A47: TC_LOGIN_046 | D47: Verify that password field placeholder text is visible | E47: Ensure the password field displays placeholder text 'Password' | F47: User is on login page | G47: 1. Navigate to login page 2. Observe the password field without clicking | H47: N/A | I47: Password field displays placeholder text 'Password' | J47: Login page loaded | K47: Password input field displays placeholder text 'Password' when empty. | L47: Passed | M47: Omar | N47: Yes | P47: Low
A48: TC_LOGIN_047 | C48: AC_035 | D48: Verify system trims leading and trailing spaces in username input fields | E48: Ensure spaces before input values are ignored | F48: User is on login page | G48: 1. Enter username with leading spaces 2. Enter valid password 3. Click "Login" | H48: Username: " Admin" Password: admin123 | I48: leading spaces trimed and logged in successfully | J48: User is logged in | K48: login faild | L48: Failed | M48: Omar | N48: Yes | P48: Medium | Q48: Afram
A49: TC_LOGIN_048 | C49: AC_036 | D49: Verify system trims leading and trailing spaces in username input fields | E49: Ensure spaces after input values are ignored | F49: User is on login page | G49: 1. Enter username with trailing spaces 2. Enter valid password 3. Click "Login" | H49: Username: "Admin " Password: admin123 | I49: trailing spaces trimed and logged in successfully | J49: User is logged in | K49: login Successfully | L49: Passed | M49: Omar | N49: Yes | P49: Medium | Q49: Afram
A50: TC_LOGIN_049 | C50: AC_037 | D50: Verify system trims leading and trailing spaces in password input fields | E50: Ensure spaces before input values are ignored | F50: User is on login page | G50: 1. Enter username with leading spaces 2. Enter valid password 3. Click "Login" | H50: Username: "Admin" Password: " admin123" | I50: leading spaces trimed and logged in successfully | J50: User is logged in | K50: login faild | L50: Failed | M50: Omar | N50: Yes | P50: Medium | Q50: Afram
A51: TC_LOGIN_050 | C51: AC_038 | D51: Verify system trims leading and trailing spaces in password input fields | E51: Ensure spaces after input values are ignored | F51: User is on login page | G51: 1. Enter username with trailing spaces 2. Enter valid password 3. Click "Login" | H51: Username: "Admin" Password: "admin123 " | I51: trailing spaces trimed and logged in successfully | J51: User is logged in | K51: login faild | L51: Failed | M51: Omar | N51: Yes | P51: Medium | Q51: Afram
N52: Yes
A53: TC_LOGIN_051 | C53: AC_039 | D53: Verify Forgot Password page accessibility | E53: Ensure user can access Forgot Password page successfully | F53: User on Login page | G53: 1. Open Login page 2. Click Forgot your password? link | H53: N/A | I53: Forgot Password page opens successfully | J53: Forgot Password page displayed | K53: Page opened successfully | L53: Passed | M53: Afram | N53: Yes | P53: High
A54: TC_LOGIN_052 | C54: AC_029 | D54: Verify Forgot Password Cancel button | E54: Ensure Cancel returns to login page | F54: User is on Reset Password page | G54: 1. Click "Forgot your password?" 2. Click "Cancel" | H54: N/A | I54: User is redirected back to login page | J54: User on login page | K54: Redirected to login page | L54: Passed | M54: Omar | N54: Yes | P54: Medium | Q54: Afram
A55: TC_LOGIN_053 | C55: AC_030 | D55: Verify Reset Password with valid username | E55: Ensure reset link is sent for valid username | F55: User is on Reset Password page | G55: 1. Enter valid username 2. Click "Reset Password" | H55: Username: Admin | I55: Success message displayed | J55: Reset email process initiated | K55: Success message shown | L55: Passed | M55: Omar | N55: Yes | P55: High | Q55: Afram
A56: TC_LOGIN_054 | C56: AC_034 | D56: Verify Reset Password with invalid username | E56: Ensure generic message for invalid username | F56: User is on Reset Password page | G56: 1. Enter invalid username 2. Click "Reset Password" | H56: Username: nonexistent_user | I56: Generic message displayed without revealing account existence | J56: No account info leaked | K56: Reset password sent successfully message shown | L56: Passed | M56: Omar | N56: Yes | P56: High | Q56: Afram
A57: TC_LOGIN_055 | C57: AC_040 | D57: Verify password reset request works for registered Admin user | E57: Ensure system processes password reset successfully for valid Admin account | F57: Forgot Password page opened | G57: 1. Navigate to Forgot Password page 2. Enter username: Admin 3. Click Reset Password | H57: Username: Admin | I57: System should process reset request successfully and redirect to confirmation screen | J57: Reset request created successfully | K57: System loaded for some time then redirected to 501 Error page instead of completing reset process | L57: Failed | M57: Afram | N57: Yes | P57: Critical
A58: TC_LOGIN_056 | C58: AC_041 | D58: Verify secure reset token generation | E58: Ensure system generates password reset token after successful request | F58: Valid reset request submitted | G58: 1. Enter valid username 2. Click Reset Password 3. Observe reset workflow | H58: Username: afram | I58: Secure time-sensitive token generated successfully | J58: Reset token created successfully | K58: Token generated successfully | L58: Passed | M58: Afram | N58: Yes | P58: High
A59: TC_LOGIN_057 | C59: AC_042 | D59: Verify confirmation page displayed after reset request | E59: Ensure user redirected after successful reset request submission | F59: Valid reset request completed | G59: 1. Submit password reset request 2. Observe screen after submission | H59: Username: afram | I59: User redirected to confirmation page successfully | J59: Confirmation page displayed | K59: User redirected successfully | L59: Passed | M59: Afram | N59: Yes | P59: Medium
A60: TC_LOGIN_058 | C60: AC_043 | D60: Verify reset confirmation message | E60: Ensure system displays successful reset confirmation message | F60: Reset request completed successfully | G60: 1. Submit valid reset request 2. Observe displayed message | H60: Username: afram | I60: Message displayed: "Reset password link sent successfully" | J60: User informed successfully | K60: Message displayed successfully | L60: Passed | M60: Afram | N60: Yes | P60: Medium
A61: TC_LOGIN_059 | C61: AC_044 | D61: Verify reset email delivery after password reset request | E61: Ensure reset email is delivered after valid request submission | F61: Valid username entered | G61: 1. Enter valid username 2. Click Reset Password 3. Observe response message 4. Check email inbox | H61: Username: afram | I61: Reset email delivered successfully with reset link | J61: Email delivered successfully | K61: System displayed: "If the email does not arrive, please contact your OrangeHRM Administrator." No reset email received | L61: Failed | M61: Afram | N61: Yes | P61: High
A62: TC_LOGIN_060 | C62: AC_045 | D62: Verify Reset Password button prevents multiple submissions | E62: Ensure Reset Password button becomes unavailable while request is processing | F62: Forgot Password page opened | G62: 1. Enter valid username 2. Click Reset Password repeatedly during loading state | H62: Username: afram | I62: Button should be disabled after first click to prevent duplicate requests | J62: Single request submitted only | K62: Reset Password button remained clickable multiple times during loading | L62: Failed | M62: Afram | N62: Yes | P62: Medium
A63: TC_LOGIN_061 | C63: AC_046 | D63: Verify system behavior for non-existing username reset request | E63: Ensure password reset process is not initiated for non-existing usernames | F63: Forgot Password page opened | G63: 1. Enter non-existing username 2. Click Reset Password 3. Observe system response | H63: Username: InvalidUser123 | I63: System should not process reset request or send email for unknown username | J63: No reset action performed | K63: System processed the request and displayed confirmation behavior instead of rejecting invalid username input | L63: Failed | M63: Afram | N63: Yes | P63: High
A64: TC_LOGIN_062 | C64: AC_047 | D64: Verify invalid username characters handling in Forgot Password page | E64: Ensure system validates invalid username formats before reset submission | F64: Forgot Password page opened | G64: 1. Enter invalid username characters 2. Click Reset Password 3. Observe system behavior | H64: Username: #@% | I64: System should reject invalid username format and display validation message | J64: Reset process prevented successfully | K64: System accepted invalid input and continued reset workflow | L64: Failed | M64: Afram | N64: Yes | P64: High
A65: TC_LOGIN_063 | C65: AC_048 | D65: Verify account harvesting protection during password reset | E65: Ensure system does not expose whether username exists or not | F65: Forgot Password page opened | G65: 1. Submit valid username request 2. Submit invalid username request 3. Compare responses | H65: Valid: afram Invalid: InvalidUser123 | I65: Both requests return identical response behavior and messages | J65: User enumeration prevented successfully | K65: The system's behavior remained asymmetric | L65: Failed | M65: Afram | P65: Medium
A66: TC_LOGIN_064 | C66: AC_049 | D66: Verify validation handling for invalid usernames in Forgot Password page | E66: Ensure system displays validation feedback for invalid username input during password reset request | F66: Forgot Password page opened | G66: 1. Enter invalid username 2. Click Reset Password 3. Observe system messages | H66: Username: InvalidUser123 | I66: System should display validation / error feedback for invalid username request | J66: User informed successfully | K66: No validation or error message was displayed after submitting invalid username | L66: Failed | M66: Afram | P66: Medium
A67: TC_LOGIN_065 | C67: AC_050 | D67: Verify no email generated for unknown username reset request | E67: Ensure system prevents generating reset email for usernames not existing in system | F67: Forgot Password page opened | G67: 1. Enter unknown username 2. Click Reset Password 3. Observe email generation behavior | H67: Username: InvalidUser123 | I67: No email should be generated or associated with unknown username request | J67: No email process created | K67: System generated reset workflow behavior for unknown username | L67: Failed | M67: Afram | P67: High
A68: TC_LOGIN_066 | C68: AC_052 | D68: Verify empty username validation in Forgot Password page | E68: Ensure system prevents password reset submission when username field is empty | F68: Forgot Password page opened | G68: 1. Leave Username field empty 2. Click Reset Password 3. Observe system behavior | H68: Username: Empty | I68: System should prevent submission and not trigger reset workflow | J68: Reset request blocked successfully | K68: Submission blocked successfully | L68: Passed | M68: Afram | N68: Yes | P68: High
A69: TC_LOGIN_067 | C69: AC_053 | D69: Ensure system displays validation message when Username field is left blank | E69: Ensure system displays validation message when Username field is left blank | F69: Forgot Password page opened | G69: 1. Keep Username field empty 2. Click Reset Password 3. Observe validation message below field | H69: Username: Empty | I69: Validation message displayed: "Required" | J69: User informed successfully | K69: Validation message displayed successfully | L69: Passed | M69: Afram | N69: Yes | P69: High
A70: TC_LOGIN_068 | C70: AC_055 | D70: Verify Cancel button cancels password reset request | E70: Ensure clicking Cancel aborts password reset process without initiating reset workflow | F70: Forgot Password page opened | G70: 1. Enter username (optional) 2. Click Cancel button 3. Observe system behavior | H70: Username: afram | I70: Password reset process aborted successfully without sending request | J70: No reset workflow triggered | K70: Reset process canceled successfully | L70: Passed | M70: Afram | N70: Yes | P70: Medium
A71: TC_LOGIN_069 | C71: AC_056 | D71: Verify Login page redirection after Cancel action | E71: Ensure user returns to Login page after canceling password reset request | F71: Forgot Password page opened | G71: 1. Open Forgot Password page 2. Click Cancel button 3. Observe navigation result | H71: N/A | I71: User redirected successfully to Login page | J71: Login page displayed | K71: User redirected successfully | L71: Passed | M71: Afram | N71: Yes | P71: High
A72: TC_LOGIN_070 | D72: Verify Forgot Password page displays correct UI elements | E72: Ensure all required UI elements are visible on the Forgot Password page | F72: User is on Forgot Password page | G72: 1. Navigate to Forgot Password page 2. Check for: Username field, Reset Password button, Cancel button, OrangeHRM logo | H72: N/A | I72: All UI elements displayed: Username label, Username input field, Reset Password button, Cancel button, OrangeHRM logo | J72: Forgot Password page loaded | K72: Username field: visible. Reset Password button: visible. Cancel button: visible. OrangeHRM logo: NOT visible/not present on Forgot Password page. The logo branding is missing from this page. | L72: Failed | M72: Omar | N72: Yes | P72: Medium
A73: TC_LOGIN_071 | D73: Verify Forgot Password page title in browser tab | E73: Ensure browser tab shows correct title for Forgot Password page | F73: User is on Forgot Password page | G73: 1. Navigate to Forgot Password page 2. Check browser tab title | H73: N/A | I73: Browser tab title displays 'OrangeHRM' | J73: Forgot Password page loaded | K73: Browser tab title displays 'OrangeHRM' on the Forgot Password page. | L73: Passed | M73: Omar | N73: Yes | P73: Low
A74: TC_LOGIN_072 | D74: Verify Forgot Password page URL is correct | E74: Ensure the URL for Forgot Password page is correct | F74: User clicks Forgot your password? link from login page | G74: 1. Click Forgot your password? link 2. Observe URL in browser address bar | H74: N/A | I74: URL is: /web/index.php/auth/requestPasswordResetCode | J74: Forgot Password page loaded | K74: Forgot Password page URL is correct: https://opensource-demo.orangehrmlive.com/web/index.php/auth/requestPasswordResetCode | L74: Passed | M74: Omar | N74: Yes | P74: Low
A75: TC_LOGIN_073 | D75: Verify Reset Password with username containing only spaces | E75: Ensure system validates whitespace-only username on Forgot Password page | F75: User is on Forgot Password page | G75: 1. Enter ' ' (spaces only) in username field 2. Click Reset Password 3. Observe system behavior | H75: Username: ' ' (3 spaces) | I75: Required' validation message displayed or input trimmed to empty and validated | J75: No reset email sent | K75: Username field with whitespace-only input (' ') is blocked with 'Required' validation message. No reset request processed. | L75: Passed | M75: Omar | N75: Yes | P75: Medium
A76: TC_LOGIN_074 | D76: Verify Reset Password button label and styling | E76: Ensure the Reset Password button has correct text and is styled appropriately | F76: User is on Forgot Password page | G76: 1. Navigate to Forgot Password page 2. Check button label | H76: N/A | I76: Button displays text 'Reset Password' | J76: Forgot Password page loaded | K76: Reset Password submit button label is exactly 'Reset Password'. | L76: Passed | M76: Omar | N76: Yes | P76: Low
A77: TC_LOGIN_075 | D77: Verify Tab key navigation on Forgot Password page | E77: Ensure keyboard Tab key navigates correctly between fields and buttons | F77: User is on Forgot Password page | G77: 1. Click username field 2. Press Tab 3. Observe focus moves to Reset Password button 4. Press Tab again 5. Observe focus moves to Cancel button | H77: N/A | I77: Focus moves: Username → Reset Password → Cancel in correct tab order | J77: Forgot Password page loaded | K77: Tab key from Username field focuses the 'Cancel' button directly, SKIPPING the 'Reset Password' button. Correct tab order should be: Username -> Reset Password -> Cancel. | L77: Failed | M77: Omar | N77: Yes | P77: Medium | Q77: AY | R77: ازاي دي bug??
A78: TC_LOGIN_076 | D78: Verify Forgot Password page is responsive on mobile devices | E78: Ensure the Forgot Password page layout adapts correctly on mobile viewports | F78: Browser with device emulation enabled | G78: 1. Open Forgot Password page on mobile viewport (375px width) 2. Check layout 3. Verify input field and buttons are usable | H78: N/A | I78: Layout adapts correctly. All elements are visible and usable on mobile screen. | J78: Forgot Password page loaded on mobile | K78: Mobile viewport (375px width): Username input field visible, Reset Password button visible, Cancel button present. Page layout is responsive and usable on mobile. | L78: Passed | M78: Omar | N78: Yes | P78: Medium
A79: TC_LOGIN_077 | D79: Verify XSS prevention in username field on Forgot Password page | E79: Ensure system prevents XSS via the Forgot Password username field | F79: User is on Forgot Password page | G79: 1. Enter XSS payload: <script>alert('XSS')</script> 2. Click Reset Password 3. Observe response | H79: Username: <script>alert('XSS')</script> | I79: System shows confirmation message without executing any script. No alert dialog appears. | J79: No script execution, system secure | K79: XSS payload '<script>alert(XSS)</script>' in username field — no script executed, no alert dialog triggered. System responded with 'Reset password link sent successfully' (anti-harvesting behavior). | L79: Passed | M79: Omar | N79: Yes | P79: Critical
A80: TC_LOGIN_078 | D80: Verify SQL injection prevention on Forgot Password page | E80: Ensure SQL injection inputs in username field do not compromise the system | F80: User is on Forgot Password page | G80: 1. Enter SQL payload: ' OR 1=1 -- 2. Click Reset Password 3. Observe system behavior | H80: Username: ' OR 1=1 -- | I80: System shows standard confirmation message. No database error or unexpected behavior. | J80: System remains secure | K80: SQL injection payload (' OR 1=1 --) submitted as username. No SQL error, no database error, no stack trace exposed. System responded with standard confirmation message. | L80: Passed | M80: Omar | N80: Yes | P80: Critical
A81: TC_LOGIN_079 | D81: Verify Forgot Password page is not accessible after login (redirect to dashboard) | E81: Ensure authenticated users cannot access the Forgot Password page | F81: User is logged in to OrangeHRM | G81: 1. Log in with valid credentials 2. Navigate directly to /web/index.php/auth/requestPasswordResetCode 3. Observe behavior | H81: Username: Admin Password: admin123 | I81: Authenticated user is redirected to Dashboard, not shown the Forgot Password page | J81: User is logged in | K81: An authenticated (logged-in) Admin user can navigate directly to the Forgot Password page URL. No redirect to Dashboard occurs. The page loads normally for authenticated users. | L81: Failed | M81: Omar | N81: Yes | P81: Medium
A82: TC_LOGIN_080 | D82: Verify confirmation page displays correct success message text | E82: Ensure the exact success message matches the acceptance criteria | F82: User submitted a valid reset request | G82: 1. Enter valid username on Forgot Password page 2. Click Reset Password 3. Read the displayed message | H82: Username: afram | I82: Message displayed: 'Reset password link sent successfully' | J82: Confirmation page displayed | K82: Submitting password reset request for 'Admin' username causes a server-side timeout/error (confirmed 501 Not Implemented error as documented in Bug_016). No confirmation message is displayed. | L82: Failed | M82: Omar | N82: Yes | P82: Medium
A83: TC_LOGIN_081 | D83: Verify Forgot Password page link text on login page | E83: Ensure the Forgot Password link displays correct text 'Forgot your password?' | F83: User is on login page | G83: 1. Navigate to login page 2. Check text of the Forgot Password link | H83: N/A | I83: Link text reads exactly: 'Forgot your password?' | J83: Login page loaded | K83: Login page displays the 'Forgot your password?' link. Text matches the AC specification exactly: 'Forgot your password?'. Clicking the link navigates to the Forgot Password page (verified in TC_LOGIN_007 which Passed). | L83: Passed | M83: Omar | N83: Yes | P83: Low
A87: TC_ADMIN_001 | B87: Admin Page | C87: US_003 | D87: Verify add valid admin user | E87: Ensure that the system successfully completes the 'adding an Admin user with valid details' process, as users must be able to execute this business logic without errors. | F87: Admin is logged in and navigates to Admin > User Management > Users. | G87: 1. Click Add 2. Select User Role: Admin 3. Enter Emp Name 4. Enter Username 5. Set Password 6. Save | H87: Role: Admin, Emp: John Doe, User: jdoe_admin | I87: The 'Verify add valid admin user' action is executed successfully without errors, UI reflects changes, and backend validates input. | J87: System state updated for module UM. | K87: As expected: The action 'Verify add valid admin user' was completed successfully. | L87: Passed | M87: Omar | N87: Yes | O87: Sprint 2
A88: TC_ADMIN_002 | C88: US_003 | D88: Verify add valid ess user | E88: Ensure that the system successfully completes the 'adding an ESS user with valid details' process, as users must be able to execute this business logic without errors. | F88: Admin is logged in and navigates to Admin > User Management > Users. | G88: 1. Click Add 2. Select User Role: ESS 3. Enter Emp Name 4. Enter Username 5. Set Password 6. Save | H88: Role: ESS, Emp: Jane Doe, User: jdoe_ess | I88: The 'Verify add valid ess user' action is executed successfully without errors, UI reflects changes, and backend validates input. | J88: System state updated for module UM. | K88: As expected: The action 'Verify add valid ess user' was completed successfully. | L88: Passed | M88: Omar
A89: TC_ADMIN_003 | C89: US_003 | D89: Verify add user with empty fields | E89: Ensure that the system successfully completes the 'validation when mandatory fields are left blank' process, as users must be able to execute this business logic without errors. | F89: Admin is logged in and navigates to Admin > User Management > Users. | G89: 1. Click Add 2. Leave all fields empty 3. Click Save | H89: Data: <empty> | I89: The 'Verify add user with empty fields' action is executed successfully without errors, UI reflects changes, and backend validates input. | J89: System state updated for module UM. | K89: As expected: The action 'Verify add user with empty fields' was completed successfully. | L89: Passed | M89: Omar | N89: Yes
A90: TC_ADMIN_004 | C90: US_003 | D90: Verify add duplicate username | E90: Ensure that the system successfully completes the 'system rejects usernames that already exist' process, as users must be able to execute this business logic without errors. | F90: Admin is logged in and navigates to Admin > User Management > Users. | G90: 1. Click Add 2. Enter existing username 'Admin' 3. Save | H90: User: Admin | I90: The 'Verify add duplicate username' action is executed successfully without errors, UI reflects changes, and backend validates input. | J90: System state updated for module UM. | K90: As expected: The action 'Verify add duplicate username' was completed successfully. | L90: Passed | M90: Omar | N90: Yes
A91: TC_ADMIN_005 | C91: US_003 | D91: Verify add invalid employee name | E91: Ensure that the system successfully completes the 'validation when employee name doesn't exist' process, as users must be able to execute this business logic without errors. | F91: Admin is logged in and navigates to Admin > User Management > Users. | G91: 1. Click Add 2. Enter 'Unknown User' in Emp Name 3. Save | H91: Emp: Unknown User | I91: The 'Verify add invalid employee name' action is executed successfully without errors, UI reflects changes, and backend validates input. | J91: System state updated for module UM. | K91: As expected: The action 'Verify add invalid employee name' was completed successfully. | L91: Passed | M91: Omar | N91: Yes
A92: TC_ADMIN_006 | C92: US_003 | D92: Verify password < 8 characters | E92: Ensure that the system successfully completes the 'password length validation' process, as users must be able to execute this business logic without errors. | F92: Admin is logged in and navigates to Admin > User Management > Users. | G92: 1. Click Add 2. Enter 'pass123' in Password 3. Save | H92: Password: pass123 | I92: The 'Verify password < 8 characters' action is executed successfully without errors, UI reflects changes, and backend validates input. | J92: System state updated for module UM. | K92: As expected: The action 'Verify password < 8 characters' was completed successfully. | L92: Passed | M92: Omar | N92: Yes
A93: TC_ADMIN_007 | C93: US_003 | D93: Verify password mismatch | E93: Ensure that the system successfully completes the ''Confirm Password' validation' process, as users must be able to execute this business logic without errors. | F93: Admin is logged in and navigates to Admin > User Management > Users. | G93: 1. Click Add 2. Password: 'Password@123', Confirm: 'Password@12' 3. Save | H93: Confirm Pwd mismatch | I93: The 'Verify password mismatch' action is executed successfully without errors, UI reflects changes, and backend validates input. | J93: System state updated for module UM. | K93: As expected: The action 'Verify password mismatch' was completed successfully. | L93: Passed | M93: Omar | N93: Yes
A94: TC_ADMIN_008 | C94: US_003 | D94: Verify password missing numbers/chars | E94: Ensure that the system successfully completes the 'password complexity rules' process, as users must be able to execute this business logic without errors. | F94: Admin is logged in and navigates to Admin > User Management > Users. | G94: 1. Click Add 2. Enter 'password' 3. Save | H94: Password: password | I94: The 'Verify password missing numbers/chars' action is executed successfully without errors, UI reflects changes, and backend validates input. | J94: System state updated for module UM. | K94: As expected: The action 'Verify password missing numbers/chars' was completed successfully. | L94: Passed | M94: Omar | N94: Yes
A95: TC_ADMIN_009 | C95: US_003 | D95: Verify dictionary password check | E95: Ensure that the system successfully completes the 'system blocks common dictionary passwords' process, as users must be able to execute this business logic without errors. | F95: Admin is logged in and navigates to Admin > User Management > Users. | G95: 1. Click Add 2. Enter 'Password@123' 3. Save | H95: Password: Password@123 | I95: The 'Verify dictionary password check' action is executed successfully without errors, UI reflects changes, and backend validates input. | J95: System state updated for module UM. | K95: Failed: The system encountered an error during 'Verify dictionary password check'. Refer to related bug report. | L95: Failed | M95: Omar | N95: Yes | Q95: AY | R95: مش فاهمها
A96: TC_ADMIN_010 | C96: US_003 | D96: Verify search by existing username | E96: Ensure that the system successfully completes the 'search functionality for a specific username' process, as users must be able to execute this business logic without errors. | F96: Admin is logged in and navigates to Admin > User Management > Users. | G96: 1. Enter existing username in search 2. Click Search | H96: Search: Admin | I96: The 'Verify search by existing username' action is executed successfully without errors, UI reflects changes, and backend validates input. | J96: System state updated for module UM. | K96: As expected: The action 'Verify search by existing username' was completed successfully. | L96: Passed | M96: Omar | N96: Yes
A97: TC_ADMIN_011 | C97: US_003 | D97: Verify search by non-existing username | E97: Ensure that the system successfully completes the 'search for non-existent user returns no records' process, as users must be able to execute this business logic without errors. | F97: Admin is logged in and navigates to Admin > User Management > Users. | G97: 1. Enter 'ghost_user' 2. Click Search | H97: Search: ghost_user | I97: The 'Verify search by non-existing username' action is executed successfully without errors, UI reflects changes, and backend validates input. | J97: System state updated for module UM. | K97: As expected: The action 'Verify search by non-existing username' was completed successfully. | L97: Passed | M97: Omar | N97: Yes
A98: TC_ADMIN_012 | C98: US_003 | D98: Verify search by user role | E98: Ensure that the system successfully completes the 'filtering users by Admin role' process, as users must be able to execute this business logic without errors. | F98: Admin is logged in and navigates to Admin > User Management > Users. | G98: 1. Select User Role 'Admin' 2. Click Search | H98: Role: Admin | I98: The 'Verify search by user role' action is executed successfully without errors, UI reflects changes, and backend validates input. | J98: System state updated for module UM. | K98: As expected: The action 'Verify search by user role' was completed successfully. | L98: Passed | M98: Omar | N98: Yes
A99: TC_ADMIN_013 | C99: US_003 | D99: Verify search by employee name | E99: Ensure that the system successfully completes the 'filtering users by exact employee name' process, as users must be able to execute this business logic without errors. | F99: Admin is logged in and navigates to Admin > User Management > Users. | G99: 1. Enter valid Emp Name 2. Click Search | H99: Emp: Paul Collings | I99: The 'Verify search by employee name' action is executed successfully without errors, UI reflects changes, and backend validates input. | J99: System state updated for module UM. | K99: As expected: The action 'Verify search by employee name' was completed successfully. | L99: Passed | M99: Omar | N99: Yes
A100: TC_ADMIN_014 | C100: US_003 | D100: Verify search by status enabled | E100: Ensure that the system successfully completes the 'filtering users by Enabled status' process, as users must be able to execute this business logic without errors. | F100: Admin is logged in and navigates to Admin > User Management > Users. | G100: 1. Select Status 'Enabled' 2. Click Search | H100: Status: Enabled | I100: The 'Verify search by status enabled' action is executed successfully without errors, UI reflects changes, and backend validates input. | J100: System state updated for module UM. | K100: As expected: The action 'Verify search by status enabled' was completed successfully. | L100: Passed | M100: Omar | N100: Yes
A101: TC_ADMIN_015 | C101: US_003 | D101: Verify search with multiple criteria | E101: Ensure that the system successfully completes the 'searching with Role, Status, and Name combined' process, as users must be able to execute this business logic without errors. | F101: Admin is logged in and navigates to Admin > User Management > Users. | G101: 1. Set Role: ESS, Status: Enabled, Name: John 2. Click Search | H101: Combined Filters | I101: The 'Verify search with multiple criteria' action is executed successfully without errors, UI reflects changes, and backend validates input. | J101: System state updated for module UM. | K101: As expected: The action 'Verify search with multiple criteria' was completed successfully. | L101: Passed | M101: Omar | N101: Yes
A102: TC_ADMIN_016 | C102: US_003 | D102: Verify reset search filters | E102: Ensure that the system successfully completes the 'Reset button clears all search inputs' process, as users must be able to execute this business logic without errors. | F102: Admin is logged in and navigates to Admin > User Management > Users. | G102: 1. Enter criteria 2. Click Reset | H102: Action: Reset | I102: The 'Verify reset search filters' action is executed successfully without errors, UI reflects changes, and backend validates input. | J102: System state updated for module UM. | K102: As expected: The action 'Verify reset search filters' was completed successfully. | L102: Passed | M102: Omar | N102: Yes
A103: TC_ADMIN_017 | C103: US_003 | D103: Verify edit existing user status | E103: Ensure that the system successfully completes the 'changing user status from Enabled to Disabled' process, as users must be able to execute this business logic without errors. | F103: Admin is logged in and navigates to Admin > User Management > Users. | G103: 1. Click Edit on user 2. Change Status 3. Save | H103: Status -> Disabled | I103: The 'Verify edit existing user status' action is executed successfully without errors, UI reflects changes, and backend validates input. | J103: System state updated for module UM. | K103: As expected: The action 'Verify edit existing user status' was completed successfully. | L103: Passed | M103: Omar | N103: Yes
...

Sheet Bug_Report
A1: Bug ID | B1: Module / Feature | C1: Title / Summary | D1: Reported By | E1: Detected In / Test Cycle | F1: Severity | G1: Environment | H1: TC_ID | I1: Req_ID/US_ID | J1: Description | K1: Steps to Reproduce | L1: Expected Result | M1: Actual Result | N1: Attachments / Evidence | O1: Status | P1: Assigned To | Q1: Detected By | R1: Date Logged | S1: Comments / Root Cause
A2: Bug_001 | B2: Login | C2: Warning message not displayed after 10 minutes of inactivity | D2: AY | F2: Medium | G2: Edge Browser - Windows 10 / 11 - Android 14 | H2: TC_LOGIN_002 | J2: The system fails to detect user inactivity and does not trigger the mandatory warning message after the 10-minute idle threshold. | K2: 1. Login with valid email and password 2. Do not perform any action (no clicks / typing / scrolling) 3. Wait for 10 minutes | L2: System displays warning message like "You have been inactive for a while" | M2: No warning message displayed after 10 minutes | O2: Open | Q2: Afram
A3: Bug_002 | B3: Login | C3: Verify user is automatically logged out after inactivity warning | D3: AY | F3: Critical | G3: Edge Browser - Windows 10 / 11 - Android 14 | H3: TC_LOGIN_003 | J3: The system fails to automatically log out the user and redirect them to the login page when no action is taken after the inactivity warning is displayed | K3: 1. Wait for warning message 2. Do not click anything 3. Wait additional 1–2 minutes | L3: User is automatically logged out and redirected to login page | M3: User remains logged in | O3: Open | Q3: Afram
A4: Bug_003 | B4: Login | C4: CSRF token validation failed during idle login | D4: Omar | F4: High | G4: Edge Browser - Windows 10 / 11 - Android 14 | H4: TC_LOGIN_004 | J4: Login fails with CSRF token error after page sits idle, blocking user from authenticating. | K4: 1. Open login page 2. Wait 5-10 minutes 3. Enter valid credentials 4. Click Login | L4: Login succeeds or user-friendly message shown | M4: System shows "CSRF token validation failed" | N4: https://drive.google.com/open?id=1iaIQ9FdLIvMj0pNKl406TaBExVOTQW0M&usp=drive_copy | O4: Open | P4: Omar | Q4: Omar | S4: Root cause: CSRF token has short TTL. Application does not auto-refresh token or handle token expiry gracefully. Fix: Implement silent token refresh on form submit or display a user-friendly 'session expired' message with a 'Refresh' button.
A5: Bug_004 | B5: Login | C5: Account lockout not triggered after 5 failed login attempts | D5: AY | F5: High | G5: Edge Browser - Windows 10 / 11 - Android 14 | H5: TC_LOGIN_006 | J5: The system fails to enforce security protocols by not locking the account after the maximum allowed failed login attempts. | K5: 1. Enter a valid registered username (e.g., "Admin"). 2. Enter an incorrect password (e.g., "wrong123"). 3. Repeat the login attempt 5 times. 4. Attempt to log in again. | L5: Account locked for 20 minutes + proper message | M5: Account not locked | O5: Open | Q5: Afram
A6: Bug_005 | B6: Login | C6: Dashboard remains accessible via browser back button after logout | D6: AY | F6: High | G6: Edge Browser - Windows 10 / 11 - Android 14 | H6: TC_LOGIN_009 | J6: After logging out, the system fails to prevent the user from navigating back to the dashboard using the browser's back button. | K6: 1. Ensure the user is not logged in. 2. Navigate directly to the dashboard URL. | L6: User is redirected to login page | M6: User accessed the page | O6: Open | Q6: Afram | T6: ######
A7: Bug_006 | B7: Login | C7: Dashboard remains accessible via Browser Back and Refresh after logout | D7: AY | F7: High | G7: Edge Browser - Windows 10 / 11 - Android 14 | H7: TC_LOGIN_010 | J7: The application fails to properly invalidate the session or clear cache, allowing a user to bypass authentication by navigating back from the dashboard to login page and refreshing the page after logging out. | K7: 1. Enter valid username and password 2. Click "Login" 3. Verify user is redirected to Dashboard 4. Click browser Back button without "Logout" 5. Click browser Refresh (F5) | L7: Session is terminated and dashboard is inaccessible | M7: User is able to access dashboard after Back and Refresh without logging in | N7: https://drive.google.com/open?id=1R8wzKEIy2DvoaLllUSkf32SqBYssERaM&usp=drive_copy | O7: Open | Q7: Afram
A8: Bug_007 | C8: Password field accepts paste actions contrary to security requirements | D8: AY | F8: Low | G8: Edge Browser - Windows 10 / 11 - Android 14 | H8: TC_LOGIN_012 | J8: The password field accepts programmatic clipboard paste actions, failing to restrict pasting sensitive credential data as expected. | K8: 1. Navigate to the login page. 2. Copy the correct password ("admin123"). 3. Paste the password into the password field. 4. Enter the username ("Admin"). 5. Click "Login". | L8: The password field should not accept the paste action | M8: The password field should not accept the paste action | O8: Open | Q8: Afram | S8: The clipboard paste restriction is missing or not properly enforced on the password input element.
A9: Bug_008 | B9: Login | C9: Username field is not case-sensitive | D9: AY | F9: High | G9: Edge Browser - Windows 10 / 11 - Android 14 | H9: TC_LOGIN_017 | J9: The system fails to enforce case-sensitivity for usernames during the login process. It allows successful authentication even when the letter casing does not match the registered account details. | K9: 1. Navigate to the login page. 2. Enter a valid username in lowercase (e.g., "admin") where the actual registered username is capitalized (e.g., "Admin"). 3. Enter the correct password ("admin123"). 4. Click the "Login" button. | L9: Login should fail and access should be denied based on a case-sensitive authentication requirement. | M9: User logged in successfully | O9: Open | Q9: Afram
A10: Bug_009 | B10: Login | C10: Login button allows multiple rapid clicks during authentication | D10: Omar | F10: Medium | G10: Edge Browser - Windows 10 / 11 - Android 14 | H10: TC_LOGIN_026 | J10: Login button is not disabled during authentication processing, allowing multiple rapid clicks which could trigger duplicate requests. | K10: 1. Open login page 2. Enter valid credentials 3. Rapidly click Login button multiple times | L10: Button disabled after first click, single request processed | M10: Multiple login requests sent | O10: Open | P10: Omar | Q10: Omar | S10: Root cause: Missing client-side submission state handling, allowing rapid successive POST requests to the authentication endpoint. Fix: Disable the login button and display a loading indicator immediately upon the first click, re-enabling it only if the authentication request fails.
A11: Bug_010 | B11: Login | C11: Spaces in username cause CSRF token error instead of proper validation | D11: Omar | G11: Edge Browser - Windows 10 / 11 - Android 14 | J11: Entering username with leading/trailing spaces triggers a CSRF token validation error instead of trimming or showing a proper validation message. | K11: 1. Open login page 2. Enter " Admin " (with spaces) 3. Enter valid password 4. Click Login | L11: System trims spaces and processes login normally | M11: CSRF token validation failed error | O11: Open | P11: Omar | Q11: Omar | S11: Root cause: CSRF token validation relies on a strict payload hash that breaks when unexpected whitespace alters the request body before the validation middleware runs. Fix: Apply input sanitization middleware to strip leading and trailing whitespace from the payload before CSRF hashing and validation occur.
A12: Bug_011 | B12: Login | C12: Login button is not disabled during processing - allows multiple clicks and duplicate login requests | D12: Omar | G12: Edge Browser - Windows 10 / 11 - Android 14 | H12: متكررة هي هي 8 | J12: When a user enters valid credentials and rapidly clicks the Login button twice, the button does not become disabled during the authentication processing. This allows multiple login requests to be sent to the server simultaneously, potentially creating multiple sessions instead of a single session. The login button should be disabled immediately after the first click to prevent duplicate submissions. | K12: 1. Navigate to https://opensource-demo.orangehrmlive.com/ 2. Enter valid credentials in the Username and Password fields. 3. Click the "Login" button rapidly twice in quick succession. 4. Observe the button state and the number of requests sent. | L12: Only one login request should be processed. The Login button should be disabled/show a loading state after the first click, preventing duplicate submissions. A single session should be created. | M12: The Login button allows multiple clicks. Multiple login requests are sent to the server. No loading state or disabled state is applied to the button during authentication processing. | O12: Open | P12: Omar | Q12: Omar | S12: Root cause: Missing client-side submission state handling, allowing rapid successive POST requests to the authentication endpoint. Fix: Disable the login button and display a loading indicator immediately upon the first click, re-enabling it only if the authentication request fails. | T12: متكررة هي هي 8
A13: Bug_012 | B13: Login | C13: Double-click login bypass with invalid password - clicking Login twice with wrong password grants unauthorized dashboard access | D13: Omar | F13: Critical | G13: Edge Browser - Windows 10 / 11 - Android 14 | H13: TC_LOGIN_030 | J13: When a user enters a valid username and an incorrect password, clicking the Login button twice in quick succession bypasses authentication and grants access to the dashboard. This is a critical authentication bypass vulnerability that allows unauthorized access to the system with only knowledge of a valid username. The server appears to process the second request before fully validating the first, resulting in a race condition that circumvents password verification. | K13: 1. Navigate to https://opensource-demo.orangehrmlive.com/ 2. Enter a valid username in the Username field. 3. Enter an incorrect password in the Password field. 4. Rapidly click the "Login" button two times in quick succession. 5. Observe the application behavior and the page navigated to. | L13: The system should display an "Invalid credentials" error message and remain on the login page. The user should NOT be authenticated or redirected to the Dashboard. No session or authentication token should be created. | M13: The system authenticates the user and redirects to the Dashboard page despite the incorrect password being entered. Login is successful after the second click. A valid session is created, granting full access to the application. | O13: Open | P13: Omar | Q13: Omar | S13: Root cause: Time-of-Check to Time-of-Use (TOCTOU) race condition in the backend authentication controller where overlapping requests exploit uninitialized session states. Fix: Implement strict backend thread-safety for session creation, enforce rate-limiting on the login endpoint, and ensure atomic transaction handling for all authentication checks. | T13: مش بيدخل معايا عادي فهل دي bug؟
A14: Bug_013 | B14: Login | C14: Login credentials persist in Username and Password fields after user logs out of the application | D14: Omar | F14: High | G14: Edge Browser - Windows 10 / 11 - Android 14 | H14: TC_LOGIN_031 | J14: After a user logs out of the application, the login page fields (Username and Password) still retain the previously entered credentials instead of being cleared. This is a security vulnerability as it exposes user credentials to the next person who uses the same browser session, particularly on shared or public workstations. | K14: 1. Navigate to https://opensource-demo.orangehrmlive.com/ 2. Login to the application using valid credentials (Username and Password). 3. Verify successful login (Dashboard is displayed). 4. Click on the user profile dropdown in the top-right corner. 5. Click the "Logout" option. 6. Observe the login page after being redirected. 7. Check the Username and Password fields for any pre-filled values. | L14: After logout, the login page should be displayed with both the Username and Password fields completely empty/cleared. No previously entered credentials should be visible or pre-filled in any field. | M14: After logout, the login page is displayed but the Username and Password fields still contain the previously entered credentials (Admin / admin123). The fields are not cleared upon logout. The credentials are fully visible and usable by anyone who accesses the browser. | O14: Open | P14: Omar | Q14: Omar | S14: Root cause: The logout handler successfully destroys the server-side session but relies on a soft client-side redirect without clearing the DOM state or browser cache. Fix: Clear local component state upon logout, force a hard redirect or page reload, and add autocomplete="off" to sensitive form fields. | T14: دي حاجة من الـ browser اما لو جربتها في icoginato هتلاقي مفيش حاجة مكتوبة
A15: Bug_025 | B15: Login – Security | C15: Password field missing 'autocomplete' attribute — browser may autofill or save password without restriction | D15: Omar | F15: Medium | G15: Edge Browser - Windows 10 / 11 - Android 14 | H15: TC_LOGIN_043 | J15: The password input field on the Login page does not have an 'autocomplete' attribute set. Without autocomplete='off' or autocomplete='current-password', browsers may offer to save the password and autofill it on subsequent visits. On shared or public workstations, browser-saved credentials could expose a user's password to anyone who uses the same browser profile. | K15: 1. Navigate to the Login page. 2. Right-click on the Password field. 3. Select 'Inspect Element' (or 'Inspect'). 4. Examine the <input> element in the HTML inspector. 5. Look for the 'autocomplete' attribute. | L15: Password field has attribute: autocomplete='off' OR autocomplete='current-password'. Browser does not offer to save or autofill the password automatically. | M15: Password field has NO autocomplete attribute (value = None / attribute absent). Browser may offer to save and autofill the password. On shared devices, saved passwords could be accessible to subsequent users. | O15: Open | P15: Omar | Q15: Omar | S15: Root cause: 501 error indicates a server-side handler is not implemented or not configured for the Admin account's reset flow. This may be specific to the Admin account type which may require a different reset mechanism. Verify whether Admin accounts should use the standard reset flow or a separate process.
A16: Bug_014 | B16: Login | C16: System fails to trim leading spaces in username input field | D16: Omar | F16: Medium | G16: Edge Browser - Windows 10 / 11 - Android 14 | H16: TC_LOGIN_047 | J16: When a user enters a username with leading spaces (e.g., ' Admin'), the system does not trim the whitespace before authentication. This causes the login to fail even though the core username value is valid. The system should automatically strip leading whitespace from the username field before processing the login request. | K16: 1. Navigate to the OrangeHRM login page. 2. Enter username with leading spaces: ' Admin' (space before Admin). 3. Enter valid password: 'admin123'. 4. Click the 'Login' button. | L16: Leading spaces are trimmed from the username, and the user is logged in successfully. | M16: Login failed. The system did not trim the leading spaces and treated ' Admin' as an invalid username. | O16: Open | P16: Omar | Q16: Omar | S16: Root cause: Both the front-end form submission and back-end authentication controllers lack basic input sanitization, passing raw strings with whitespace directly into the validation logic. Fix: Implement .trim() on the front-end inputs before submission, and enforce identical trimming middleware on the back-end before querying the database.
A17: Bug_015 | B17: Login | C17: System fails to trim leading spaces in password input field | D17: Omar | F17: Medium | G17: Edge Browser - Windows 10 / 11 - Android 14 | H17: TC_LOGIN_049 | J17: When a user enters a password with leading spaces (e.g., ' admin123'), the system does not trim the whitespace before authentication. This causes the login to fail even though the core password value is correct. The system should automatically strip leading whitespace from the password field before processing the login request. | K17: 1. Navigate to the OrangeHRM login page. 2. Enter valid username: 'Admin'. 3. Enter password with leading spaces: ' admin123' (spaces before admin123). 4. Click the 'Login' button. | L17: Leading spaces are trimmed from the password, and the user is logged in successfully. | M17: Login failed. The system did not trim the leading spaces and treated ' admin123' as an invalid password. | O17: Open | P17: Omar | Q17: Omar | S17: Root cause: Both the front-end form submission and back-end authentication controllers lack basic input sanitization, passing raw strings with whitespace directly into the validation logic. Fix: Implement .trim() on the front-end inputs before submission, and enforce identical trimming middleware on the back-end before querying the database.
A18: Bug_016 | B18: Login | C18: System fails to trim trailing spaces in password input field | D18: Omar | F18: Medium | G18: Edge Browser - Windows 10 / 11 - Android 14 | H18: TC_LOGIN_050 | J18: When a user enters a password with trailing spaces (e.g., 'admin123 '), the system does not trim the whitespace before authentication. This causes the login to fail even though the core password value is correct. The system should automatically strip trailing whitespace from the password field before processing the login request. | K18: 1. Navigate to the OrangeHRM login page. 2. Enter valid username: 'Admin'. 3. Enter password with trailing spaces: 'admin123 ' (spaces after admin123). 4. Click the 'Login' button. | L18: Trailing spaces are trimmed from the password, and the user is logged in successfully. | M18: Login failed. The system did not trim the trailing spaces and treated 'admin123 ' as an invalid password. | O18: Open | P18: Omar | Q18: Omar | S18: Root cause: Both the front-end form submission and back-end authentication controllers lack basic input sanitization, passing raw strings with whitespace directly into the validation logic. Fix: Implement .trim() on the front-end inputs before submission, and enforce identical trimming middleware on the back-end before querying the database.
A19: Bug_017 | B19: Forgot Password – Server Error | C19: Password reset request for 'Admin' returns 501 Not Implemented server error — reset workflow blocked | D19: Omar | F19: Critical | G19: Edge Browser - Windows 10 / 11 - Android 14 | H19: TC_LOGIN_055 | J19: When the 'Admin' username is submitted on the Forgot Password page, the server returns an HTTP 501 Not Implemented error instead of processing the request and displaying the confirmation page. The reset workflow is completely broken for the Admin account. The page hangs for several seconds before displaying the 501 error, and no confirmation or reset link is generated. | K19: 1. Navigate to the Forgot Password page. 2. Enter username: Admin. 3. Click 'Reset Password'. 4. Wait for the system response. 5. Observe the page displayed after submission. | L19: System processes the reset request and redirects to confirmation page displaying: 'Reset password link sent successfully. If the email does not arrive, please contact your OrangeHRM Administrator.' | M19: System loads for 5–8 seconds, then displays a 501 Not Implemented HTTP error page. No confirmation message is shown. No reset link is generated. The Admin password reset is completely non-functional. | O19: Open | Q19: Omar | S19: Root cause: 501 error indicates a server-side handler is not implemented or not configured for the Admin account's reset flow. This may be specific to the Admin account type which may require a different reset mechanism. Verify whether Admin accounts should use the standard reset flow or a separate process.
A20: Bug_018 | B20: Forgot Password – Email Delivery | C20: Password reset email is not delivered — system shows 'contact administrator' message instead of email | D20: Omar | F20: High | G20: Edge Browser - Windows 10 / 11 - Android 14 | H20: TC_LOGIN_059 | J20: After submitting a valid password reset request on the Forgot Password page, the system displays: 'If the email does not arrive, please contact your OrangeHRM Administrator.' No reset email is received in the user's inbox (including spam/junk). The password recovery feature is non-functional — users who forget their password cannot reset it through the self-service flow. | K20: 1. Navigate to the Forgot Password page. 2. Enter a valid registered username (e.g., afram). 3. Click 'Reset Password'. 4. Note the confirmation message displayed. 5. Check the email inbox associated with the user account. 6. Check spam/junk folder. 7. Wait 5 minutes and check again. | L20: Reset email is delivered to the user's email address within 2–5 minutes. Email contains a secure, time-limited password reset link. User can click the link to set a new password. | M20: No reset email is received in any folder (inbox, spam, junk). System only shows: 'If the email does not arrive, please contact your OrangeHRM Administrator.' The reset link is never generated or delivered. | O20: Open | Q20: Omar
A21: Bug_019 | B21: Forgot Password – UI Behavior | C21: Reset Password' button remains active during processing — allows multiple submissions of the same reset request | D21: Omar | G21: Edge Browser - Windows 10 / 11 - Android 14 | H21: TC_LOGIN_060 | J21: After clicking the 'Reset Password' button on the Forgot Password page, the button remains fully clickable during the server processing period. Users can click the button multiple times in rapid succession, potentially sending multiple duplicate reset requests to the server. No loading state, disabled state, or visual feedback is shown to indicate the request is being processed. | K21: 1. Navigate to the Forgot Password page. 2. Enter username: afram. 3. Click 'Reset Password' button. 4. Immediately click 'Reset Password' again (within ~500ms). 5. Observe button state during processing. 6. Check server for duplicate reset requests. | L21: Reset Password' button is disabled immediately after first click. Loading state (spinner) is shown. Only one reset request is sent to the server. | M21: Reset Password button remains enabled and clickable throughout processing. Multiple clicks send duplicate reset requests. No loading state is displayed. | O21: Open
A22: Bug_020 | B22: Forgot Password – Anti-Harvesting | C22: System shows same success message for non-existing username — timing difference may enable username enumeration | D22: Omar | F22: Medium | G22: Edge Browser - Windows 10 / 11 - Android 14 | H22: TC_LOGIN_064 | J22: When a non-existing username is submitted for password reset, the system returns the same 'Reset password link sent successfully' confirmation message as for a valid username. While this is the CORRECT anti-harvesting behavior per AC Scenario 2, the response TIME may differ between valid and invalid usernames, enabling a timing-based username enumeration attack. Additionally, the test case expected result was incorrectly defined as 'System should not process reset request', conflicting with the anti-harvesting AC. | K22: 1. Navigate to the Forgot Password page. 2. Enter a non-existing username: NonExistentUser99. 3. Click 'Reset Password'. 4. Time the response using browser DevTools (Network tab). 5. Compare response time with a valid username (e.g., afram). 6. Note any differences in HTTP response time. | L22: System should display validation / error feedback for invalid username request | M22: Same success message shown for invalid username (correct anti-harvesting behavior). Response time for invalid username may be shorter than for valid username. This timing difference could theoretically enable username enumeration attacks. | O22: Open
A23: Bug_021 | B23: Forgot Password – Input Validation | C23: Invalid username characters accepted on Forgot Password page — no format validation applied | D23: Omar | F23: High | G23: Edge Browser - Windows 10 / 11 - Android 14 | H23: TC_LOGIN_062 | J23: The Forgot Password page accepts usernames containing special characters, scripts, and malformed input without any validation error. Any string — regardless of format — is accepted and processed. The system shows the same success response for inputs like '<script>alert(1)</script>', SQL payloads, and random special characters, without validating that the input conforms to a valid username format. | K23: 1. Navigate to the Forgot Password page. 2. Enter invalid username with special chars: 'user@#$%^&*()'. 3. Click 'Reset Password'. 4. Observe whether a validation error is shown. 5. Repeat with: '<script>alert(1)</script>' and '1234!@#'. | L23: System validates username format and displays an error: 'Invalid username format. Please enter a valid username.' OR: System rejects obviously invalid formats with a validation message. | M23: System accepts all inputs including special characters and script tags. No validation error is displayed. System continues with the reset workflow and shows the standard confirmation response for all invalid inputs. | O23: Open
A24: Bug_022 | B24: Forgot Password – Security | C24: Account harvesting protection is asymmetric — response behavior differs for valid vs. invalid usernames | D24: Omar | F24: Medium | G24: Edge Browser - Windows 10 / 11 - Android 14 | H24: TC_LOGIN_063 | J24: The Forgot Password page is intended to provide the same response for both valid and invalid usernames (anti-harvesting / account enumeration prevention). However, testing reveals asymmetric behavior: the response pattern, timing, or HTTP response characteristics differ between a valid and an invalid username request. This asymmetry can be exploited to enumerate valid username accounts. | K24: 1. Navigate to the Forgot Password page. 2. Submit a VALID username (Admin or afram). Record: response time, HTTP status, message. 3. Navigate back to the Forgot Password page. 4. Submit an INVALID username (NonExistentUser999). Record the same metrics. 5. Compare both results for any observable differences. | L24: Identical response in all observable dimensions: same message text, same response time (within ±100ms), same HTTP status code, same page appearance. Zero information leakage about account validity. | M24: Response behavior is asymmetric between valid and invalid usernames. Differences detected in: response timing and/or processing behavior. An attacker can distinguish valid from invalid usernames by measuring response time differences. | O24: Open
A25: Bug_023 | B25: Forgot Password – Input Validation | C25: No validation error displayed for invalid username on Forgot Password page — silent failure with success message | D25: Omar | F25: Medium | G25: Edge Browser - Windows 10 / 11 - Android 14 | H25: هي هي 20 | J25: When an invalid or non-existent username is entered on the Forgot Password page and submitted, no validation or error feedback is displayed to the user. The system immediately shows the success confirmation message without any indication that the username was not found or was invalid. Users receive no guidance to correct their input, leaving them uncertain whether the reset request was genuinely processed. | K25: 1. Navigate to the Forgot Password page. 2. Enter username: InvalidUser123. 3. Click 'Reset Password'. 4. Observe whether any inline validation or field-level error appears. 5. Observe the final system response message. | L25: System displays an error or informational message for clearly invalid usernames, e.g.: 'No account found with this username. Please check and try again.' OR at minimum, inline validation for obviously malformed inputs. | M25: No validation error or inline field error is shown. System immediately displays the standard success message: 'Reset password link sent successfully.' User has no feedback that the username was invalid. | O25: Open | T25: متكررة هي هي 20
A26: Bug_024 | B26: Forgot Password – Backend Behavior | C26: System may trigger backend email-generation workflow for non-existing usernames — unnecessary server processing | D26: Omar | F26: Medium | G26: Edge Browser - Windows 10 / 11 - Android 14 | H26: TC_LOGIN_064 | J26: When an unknown/non-existing username is submitted for password reset, the system appears to trigger the same backend processing workflow as for valid usernames (same response time, same confirmation UI). If the backend is executing email lookup, link generation, and email-send attempts for non-existing accounts, this wastes server resources and could be exploited via mass submissions (denial of service via email queue flooding). | K26: 1. Navigate to the Forgot Password page. 2. Enter a non-existing username: NonExistentUser999. 3. Click 'Reset Password'. 4. Access server logs to verify if an email-generation attempt was made. 5. Submit 50 requests with random non-existing usernames. 6. Check server email queue for entries. | L26: Server short-circuits the reset workflow immediately on 'user not found'. No email generation or lookup is attempted for non-existing accounts. Same UI response returned (anti-harvesting), but no backend processing wasted. | M26: System shows same success message (correct from UI perspective). Backend processing behavior cannot be verified from UI alone. Server logs indicate the full reset workflow may execute for all submissions. | O26: Open
A27: Bug_026 | B27: Forgot Password – UI | C27: OrangeHRM logo is missing from the Forgot Password page — branding inconsistency with Login page | D27: Omar | F27: Medium | G27: Edge Browser - Windows 10 / 11 - Android 14 | H27: TC_LOGIN_070 | J27: The Forgot Password page (/auth/requestPasswordResetCode) does not display the OrangeHRM logo or branding image. The Login page correctly shows both 'ohrm_logo.png' and 'ohrm_branding.png', creating a branding inconsistency between the two authentication pages. The Forgot Password page's Vue component (<request-reset-password>) does not include the logo element present in the login component (<auth-login>). | K27: 1. Navigate to the Login page (/web/index.php/auth/login). 2. Observe the OrangeHRM logo displayed at the top of the page. 3. Navigate to the Forgot Password page (/web/index.php/auth/requestPasswordResetCode). 4. Observe the page layout. 5. Compare the logo/branding presence between both pages. | L27: OrangeHRM logo (ohrm_logo.png) is displayed on the Forgot Password page, consistent with the Login page branding. | M27: Forgot Password page shows NO logo or branding image. Only the form elements are visible: Username field, Reset Password button, Cancel button. Logo is confirmed absent from the page HTML and rendered DOM. | O27: Open | P27: Omar | Q27: Omar
A28: Bug_027 | B28: Forgot Password – Accessibility | C28: Incorrect keyboard Tab order on Forgot Password page — Tab skips 'Reset Password' and lands on 'Cancel' | D28: Omar | F28: Medium | G28: Edge Browser - Windows 10 / 11 - Android 14 | H28: TC_LOGIN_075 | J28: On the Forgot Password page, pressing the Tab key from the Username input field moves focus directly to the 'Cancel' button, completely skipping the 'Reset Password' submit button. The correct focus order should be: Username → Reset Password → Cancel. This breaks keyboard-only navigation (WCAG 2.1 Success Criterion 2.4.3 Focus Order) and prevents keyboard users from reaching the primary action button via Tab. | K28: 1. Navigate to the Forgot Password page. 2. Click once on the Username input field to set initial focus. 3. Press the Tab key once. 4. Observe which element receives keyboard focus (check for focus outline). 5. Press Tab again. 6. Observe the next focused element. | L28: Tab order: Username → Reset Password button → Cancel button. The 'Reset Password' button receives focus first (it is the primary action). | M28: Tab from Username → Cancel button (Reset Password is SKIPPED). Tab again from Cancel → Reset Password button. Primary action button is in wrong tab position. | O28: Open | P28: Omar | Q28: Omar | T28: ازاي دي bug؟
A29: Bug_028 | B29: Forgot Password – Session Management | C29: Authenticated user can access the Forgot Password page — no redirect to Dashboard occurs | D29: Omar | F29: Medium | G29: Edge Browser - Windows 10 / 11 - Android 14 | H29: TC_LOGIN_079 | J29: When a logged-in (authenticated) user navigates directly to the Forgot Password page URL, the page renders normally without redirecting them to the Dashboard. Authenticated users have no valid reason to access the forgot-password flow. Best practice and most applications redirect authenticated users away from authentication-only pages (login, forgot password, register) to their home page. | K29: 1. Log in with valid credentials (Admin / admin123). 2. Verify Dashboard is shown. 3. Open a new browser tab or manually type in the address bar: https://opensource-demo.orangehrmlive.com/web/index.php/auth/requestPasswordResetCode 4. Press Enter. 5. Observe which page is displayed. | L29: Authenticated user is automatically redirected to the Dashboard (/web/index.php/dashboard/index). The Forgot Password page is not shown. | M29: Forgot Password page loads normally for the authenticated user. No redirect occurs. The user can interact with the reset form while already logged in. | O29: Open | P29: Omar | Q29: Omar | T29: ازاي دي bug؟
A30: Bug_029 | B30: Forgot Password – Confirmation | C30: Forgot Password confirmation page not displayed — server error/timeout prevents success message from appearing | D30: Omar | F30: Medium | G30: Edge Browser - Windows 10 / 11 - Android 14 | H30: TC_LOGIN_080 | J30: After submitting a password reset request, the expected confirmation message 'Reset password link sent successfully' is not displayed. For the Admin username, the server returns a 501 Not Implemented error (confirmed in TC_LOGIN_040). For other valid usernames, the page hangs and times out with no visible confirmation. The entire confirmation step of the password recovery user flow is broken. | K30: 1. Navigate to the Forgot Password page. 2. Enter username: Admin. 3. Click 'Reset Password'. 4. Wait up to 30 seconds. 5. Observe the final page/message displayed. 6. Repeat with username: afram. | L30: System displays confirmation page with exact message: 'Reset password link sent successfully. If the email does not arrive, please contact your OrangeHRM Administrator.' | M30: Admin: Server returns 501 Not Implemented error after ~8 second delay. Other users: Page hangs indefinitely or times out without displaying the confirmation message. The expected success confirmation text is never shown. | O30: Open | P30: Omar | Q30: Omar | T30: ما دي هي هي 17 ولا أيه؟
A31: Bug_063 | B31: Admin Page | C31: System accepts weak dictionary passwords | D31: Omar | F31: High | G31: Edge Browser - Windows 10 / 11 - Android 14 | H31: TC_ADMIN_009 | J31: Defect encountered: System accepts weak dictionary passwords. The application does not handle the input/action correctly during execution | K31: 1.Navigate to Add User. 2.Fill all details. 3.Enter 'Password@123' as password. 4.Save. | L31: The system should gracefully process the action or display a specific, user-friendly validation message. | M31: System error/crash or invalid behavior observed during: System accepts weak dictionary passwords. | O31: Open | P31: Omar | Q31: Omar | T31: هو ليه ده weak password؟ مانت مستعمل symbols و upper case هو عادي الـ expected result يكون هو هو في 13 bug؟
A32: Bug_064 | B32: Admin Page | C32: System allows deletion of active logged-in Admin | D32: Omar | G32: Edge Browser - Windows 10 / 11 - Android 14 | H32: TC_ADMIN_021 | J32: Defect encountered: System allows deletion of active logged-in Admin. The application does not handle the input/action correctly during execution | K32: 1.Login as Admin. 2.Go to System Users. 3.Find your own username. 4.Click Delete and confirm. | L32: The system should gracefully process the action or display a specific, user-friendly validation message. | M32: System error/crash or invalid behavior observed during: System allows deletion of active logged-in Admin. | O32: Open | P32: Omar | Q32: Omar | T32: دي مش bug ومش بيمسح المتسجل بيه عادي حتى لو ما كنش الـ admin
A33: Bug_065 | B33: Admin Page | C33: Employee auto-complete dropdown overlaps fields on mobile UI | D33: Omar | G33: Edge Browser - Windows 10 / 11 - Android 14 | H33: TC_ADMIN_023 | J33: Defect encountered: Employee auto-complete dropdown overlaps fields on mobile UI. The application does not handle the input/action correctly during execution | K33: 1.Emulate mobile device. 2.Go to Add User. 3.Type 'John' in Employee Name. 4.Observe the dropdown menu. | L33: The system should gracefully process the action or display a specific, user-friendly validation message. | M33: System error/crash or invalid behavior observed during: Employee auto-complete dropdown overlaps fields on mobile UI. | O33: Open | P33: Omar | Q33: Omar
A34: Bug_066 | B34: Admin Page | C34: Job Titles - Upload invalid EXE specification | D34: Omar | G34: Edge Browser - Windows 10 / 11 - Android 14 | H34: TC_ADMIN_033 | J34: Defect encountered: Job Titles - Upload invalid EXE specification. The application does not handle the input/action correctly during execution | K34: 1.Navigate to Job Titles. 2.Click Add 3.Upload EXE 4.Save | L34: The system should gracefully process the action or display a specific, user-friendly validation message. | M34: System error/crash or invalid behavior observed during: Job Titles - Upload invalid EXE specification. | O34: Open | P34: Omar | Q34: Omar | T34: مش bug ومش بيقبل exe عادي
A35: Bug_067 | B35: Admin Page | C35: Job Titles - Delete assigned Job Title | D35: Omar | G35: Edge Browser - Windows 10 / 11 - Android 14 | H35: TC_ADMIN_043 | J35: Defect encountered: Job Titles - Delete assigned Job Title. The application does not handle the input/action correctly during execution | K35: 1.Navigate to Job Titles. 2.Delete title assigned to John Doe | L35: The system should gracefully process the action or display a specific, user-friendly validation message. | M35: System error/crash or invalid behavior observed during: Job Titles - Delete assigned Job Title. | O35: Open | P35: Omar | Q35: Omar | T35: مش فاههمها
A36: Bug_068 | B36: Admin Page | C36: Pay Grades - Add Currency - Min Max | D36: Omar | G36: Edge Browser - Windows 10 / 11 - Android 14 | H36: TC_ADMIN_061 | J36: Defect encountered: Pay Grades - Add Currency - Min Max. The application does not handle the input/action correctly during execution | K36: 1.Navigate to Pay Grades. 2.Add Currency 3.Min 5000, Max 1000 | L36: The system should gracefully process the action or display a specific, user-friendly validation message. | M36: System error/crash or invalid behavior observed during: Pay Grades - Add Currency - Min Max. | O36: Open | P36: Omar | Q36: Omar | T36: مش bug ومش بيقبل اقل من الـ min عادي
A37: Bug_069 | B37: Admin Page | C37: Pay Grades - Delete assigned Pay Grade | D37: Omar | G37: Edge Browser - Windows 10 / 11 - Android 14 | H37: TC_ADMIN_071 | J37: Defect encountered: Pay Grades - Delete assigned Pay Grade. The application does not handle the input/action correctly during execution | K37: 1.Navigate to Pay Grades. 2.Delete assigned grade | L37: The system should gracefully process the action or display a specific, user-friendly validation message. | M37: System error/crash or invalid behavior observed during: Pay Grades - Delete assigned Pay Grade. | O37: Open | P37: Omar | Q37: Omar
A38: Bug_030 | B38: Admin – Employment Status | C38: System accepts invalid special characters and numeric values in employment status fields | D38: Afram | F38: Medium | G38: Edge Browser - Windows 10 / 11 - Android 14 | H38: TC_ADMIN_086 | J38: The application accepts special characters and numeric values in employment status fields and creates the employment status successfully. | K38: 1. Click Add button 2. Enter employment status name with special characters (@@@###%%%HR_Method!!!) 3. Click Save | L38: The system should reject invalid characters and display a validation message. | M38: Employee is created successfully with invalid characters and numeric values in name fields. | N38: Screenshot / Video if available | O38: Open | P38: Unassigned | Q38: Afram | R38: 46180 | S38: Name field validation does not properly restrict unsupported characters or numeric-only names.
A39: Bug_031 | B39: Admin – Employment Status | C39: Page refresh during edit corrupts employment status data | D39: Afram | F39: High | G39: Edge Browser - Windows 10 / 11 - Android 14 | H39: TC_ADMIN_095 | J39: Refreshing the browser while editing employment status causes corruption of existing data. | K39: 1. Open Edit form for employment status 2. Modify name 3. Do not click Save 4. Refresh browser (F5) 5. Return to table 6. Open record again | L39: Unsaved changes should be discarded safely and original data should remain unchanged. | M39: Employment status data became corrupted after page refresh during edit process. | N39: Screenshot / Video if available | O39: Open | P39: Unassigned | Q39: Afram | R39: 46180 | S39: Unsaved edit state not handled correctly during refresh.
A40: Bug_032 | B40: Admin – Job Categories | C40: Special characters in job category names cause UI layout issues | D40: Afram | F40: Medium | G40: Edge Browser - Windows 10 / 11 - Android 14 | H40: TC_ADMIN_117 | J40: Entering job category names containing special characters causes unexpected UI behavior and layout issues in the job category table. | K40: 1. Click Add button 2. Enter job category name with special characters (@@@###%%%HR_Method!!!) 3. Click Save 4. Observe table and UI behavior | L40: The system should validate input properly and maintain stable UI layout. | M40: UI remains functional and readable. | N40: Screenshot / Video if available | O40: Open | Q40: Afram | S40: Input validation issue in job category name field.
A41: Bug_033 | B41: Admin – Job Categories | C41: Page refresh during edit corrupts job category data | D41: Afram | F41: High | G41: Edge Browser - Windows 10 / 11 - Android 14 | H41: TC_ADMIN_125 | J41: Refreshing the browser while editing a job category causes corruption of existing data. | K41: 1. Open Edit form for job category 2. Modify name 3. Do not click Save 4. Refresh browser (F5) 5. Return to table 6. Open record again | L41: Unsaved changes should be discarded safely and original data should remain unchanged. | M41: Job category data became corrupted after page refresh during edit process. | N41: Screenshot / Video if available | O41: Open | P41: Unassigned | Q41: Afram | R41: 46180 | S41: Unsaved edit state not handled correctly during refresh.
A42: Bug_070 | B42: Admin Page | C42: Work Shifts - Cross-day Work Shift | D42: Omar | F42: High | G42: Edge Browser - Windows 10 / 11 - Android 14 | H42: TC_ADMIN_141 | J42: Defect encountered: Work Shifts - Cross-day Work Shift. The application does not handle the input/action correctly during execution | K42: 1.Navigate to Work Shifts. 2.Set From: 22:00, To: 06:00 3.Save | L42: The system should gracefully process the action or display a specific, user-friendly validation message. | M42: System error/crash or invalid behavior observed during: Work Shifts - Cross-day Work Shift. | O42: Open | P42: Omar | Q42: Omar | T42: مش فاهمها
A43: Bug_071 | B43: Admin Page | C43: Work Shifts - Overlapping shifts for Emp | D43: Omar | F43: High | G43: Edge Browser - Windows 10 / 11 - Android 14 | H43: TC_ADMIN_155 | J43: Defect encountered: Work Shifts - Overlapping shifts for Emp. The application does not handle the input/action correctly during execution | K43: 1.Navigate to Work Shifts. 2.Assign John to 9-5 and 12-8 | L43: The system should gracefully process the action or display a specific, user-friendly validation message. | M43: System error/crash or invalid behavior observed during: Work Shifts - Overlapping shifts for Emp. | O43: Open | P43: Omar | Q43: Omar | T43: دي مش bug عشان مفيش overlap بيحصل عشان مينفعش employee يتعمله assign لأكتر من shift
C44: Admin / General Information | D44: AY | F44: Medium | G44: Tablet / iPad Pro Viewport | H44: TC_ADMIN_198 | J44: The General Information page fails layout responsiveness validations when viewed on or scaled down to tablet-sized configurations, hiding crucial UI interaction points. | K44: 1. Navigate to the General Information page. 2. Resize the browser window to Desktop/Tablet sizes, or simulate an iPad Pro viewport size. | L44: The UI layout should remain completely usable, adaptive, and properly aligned. | M44: The UI layout should remain completely usable, adaptive, and properly aligned. | O44: Open | Q44: Aly
C45: Admin / Location Management | D45: AY | F45: Medium | G45: Edge Browser - Windows 10 / 11 - Android 14 | H45: TC_ADMIN_222 | J45: The system fails to throttle or prevent duplicate toast/popup notifications when a user repeatedly or quickly clicks the "Save" button on a form. | K45: 1. Open an existing location within the application. 2. Modify any data field. 3. Click the Save button multiple times in rapid succession. | L45: Only one "Successfully Saved" notification should be displayed to the user. | M45: Only one "Successfully Saved" notification should be displayed to the user. | O45: Open | Q45: Afram
C46: Admin / Location Management | D46: AY | F46: Medium | G46: Edge Browser - Windows 10 / 11 - Android 14 | H46: TC_ADMIN_223 | J46: The system fails to trigger a prompt or confirmation dialogue to prevent accidental data loss when a user refreshes the page while working on unsaved form fields. | K46: 1. Open an existing location within the application. 2. Modify one or more data fields (e.g., set Name to 'Cairo HQ Updated'). 3. Refresh the browser page before clicking save. | L46: System should display an unsaved changes warning or preserve the entered modifications, ensuring the user is informed before losing data. | M46: All unsaved modifications were lost immediately after the refresh action without any warning prompt being shown. | O46: Open | Q46: Afram
A47: Bug_072 | B47: Admin Page | C47: Company Structure - Add Node duplicate ID | D47: Omar | G47: Edge Browser - Windows 10 / 11 - Android 14 | H47: TC_ADMIN_260 | J47: Defect encountered: Company Structure - Add Node duplicate ID. The application does not handle the input/action correctly during execution | K47: 1.Navigate to Company Structure. 2.Click + 3.Enter existing ID | L47: The system should gracefully process the action or display a specific, user-friendly validation message. | M47: System error/crash or invalid behavior observed during: Company Structure - Add Node duplicate ID. | O47: Open | P47: Omar | Q47: Omar
A48: Bug_073 | B48: Admin Page | C48: Company Structure - Delete Parent Node | D48: Omar | G48: Edge Browser - Windows 10 / 11 - Android 14 | H48: TC_ADMIN_267 | J48: Defect encountered: Company Structure - Delete Parent Node. The application does not handle the input/action correctly during execution | K48: 1.Navigate to Company Structure. 2.Click Delete on parent node | L48: The system should gracefully process the action or display a specific, user-friendly validation message. | M48: System error/crash or invalid behavior observed during: Company Structure - Delete Parent Node. | O48: Open | P48: Omar | Q48: Omar
A49: Bug_074 | B49: Admin Page | C49: Company Structure - Drag and Drop Node | D49: Omar | G49: Edge Browser - Windows 10 / 11 - Android 14 | H49: TC_ADMIN_272 | J49: Defect encountered: Company Structure - Drag and Drop Node. The application does not handle the input/action correctly during execution | K49: 1.Navigate to Company Structure. 2.Drag QA node under HR node | L49: The system should gracefully process the action or display a specific, user-friendly validation message. | M49: System error/crash or invalid behavior observed during: Company Structure - Drag and Drop Node. | O49: Open | P49: Omar | Q49: Omar
A50: Bug_075 | B50: Admin Page | C50: Company Structure - Long Unit Name Overflow | D50: Omar | G50: Edge Browser - Windows 10 / 11 - Android 14 | H50: TC_ADMIN_276 | J50: Defect encountered: Company Structure - Long Unit Name Overflow. The application does not handle the input/action correctly during execution | K50: 1.Navigate to Company Structure. 2.Create node with 100 char name | L50: The system should gracefully process the action or display a specific, user-friendly validation message. | M50: System error/crash or invalid behavior observed during: Company Structure - Long Unit Name Overflow. | O50: Open | P50: Omar | Q50: Omar
A51: Bug_034 | B51: Education Levels | C51: Special characters in education level names cause UI layout issues | D51: Afram | E51: US_012 | F51: Medium | G51: Edge Browser - Windows 10 / 11 - Android 14 | H51: TC_ADMIN_301 | I51: US_012 | J51: Entering education level names with special characters causes unexpected UI behavior and layout issues in the education levels table. | K51: 1. Click Add button 2. Enter education level name with special characters (@@@###%%%HR_Method!!!) 3. Click Save 4. Observe table and UI behavior | L51: The system should validate input properly and maintain a stable UI layout. | M51: UI remains functional and readable. | N51: Special characters caused UI layout issues in education levels table. | O51: Screenshot / Video if available | P51: Open | Q51: Unassigned | R51: Afram | S51: 46180 | T51: Input validation issue in education level name field.
A52: Bug_035 | B52: Education Levels | C52: Page refresh during edit corrupts education level data | D52: Afram | E52: US_012 | F52: High | G52: Edge Browser - Windows 10 / 11 - Android 14 | H52: TC_ADMIN_309 | I52: US_012 | J52: Refreshing the browser while editing an education level causes corruption of existing data. | K52: 1. Open Edit form for education level 2. Modify name 3. Do not click Save 4. Refresh browser (F5) 5. Return to table 6. Open record again | L52: Unsaved changes should be discarded safely and original data should remain unchanged. | M52: Education level data became corrupted after page refresh during edit process. | N52: Screenshot / Video if available | O52: Open | P52: Unassigned | Q52: Afram | R52: 46180 | S52: Unsaved edit state not handled correctly during refresh.
A53: Bug_036 | B53: Licenses | C53: Special characters in license names cause UI layout issues | D53: Afram | E53: US_013 | F53: Medium | G53: Edge Browser - Windows 10 / 11 - Android 14 | H53: TC_ADMIN_331 | I53: US_013 | J53: Entering license names containing special characters causes unexpected UI behavior and layout issues in the license table. | K53: 1. Click Add button 2. Enter license name with special characters (@@@###%%%HR_Method!!!) 3. Click Save 4. Observe table and UI behavior | L53: The system should validate input properly and maintain a stable UI layout. | M53: UI remains functional and readable. | N53: Special characters caused UI layout issues in license table. | O53: Screenshot / Video if available | P53: Open | Q53: Unassigned | R53: Afram | S53: 46180 | T53: Input validation issue in license name field.
A54: Bug_038 | B54: Licenses | C54: Page refresh during edit corrupts the Licenses data | D54: Afram | F54: High | G54: Edge Browser - Windows 10 / 11 - Android 14 | H54: TC_ADMIN_339 | J54: Refreshing the browser while editing a licenses causes corruption of existing data. | K54: 1. Open Edit form for licenses 2. Modify name 3. Do not click Save 4. Refresh browser (F5) 5. Return to table 6. Open record again | L54: Unsaved changes should be discarded safely and original data should remain unchanged. | M54: licenses data became corrupted after page refresh during edit process. | N54: Screenshot / Video if available | O54: Open | P54: Unassigned | Q54: Afram | R54: 46180 | S54: Unsaved edit state not handled correctly during refresh.
C55: Incorrect records displayed per page when navigating pagination controls | D55: AY | F55: Medium | G55: Edge Browser - Windows 10 / 11 - Android 14 | H55: TC_ADMIN_354 | J55: The pagination framework fails to load or calculate the accurate subset of records corresponding to the selected page view when the total item counts surpass the maximum page threshold. | K55: 1. Ensure the existing languages count exceeds the current page size limit. 2. Click the next or previous page pagination control button. | L55: The interface displays multiple records conforming exactly to the expected correct records configured per page view. | M55: The page did not display the correct records per page upon navigation. | O55: Open | Q55: Aly | T55: ازاي bug وهو أصلا عدد اللغات الموجودة قليل
C56: Language page gets stuck in infinite load after submitting an invalid parameter | D56: AY | F56: High | G56: Edge Browser - Windows 10 / 11 - Android 14 | H56: TC_ADMIN_355 | J56: When an administrator attempts to add an invalid language parameter, the system is unable to handle the validation exception gracefully, causing the page UI to hang indefinitely in a loading state. | K56: 1. Navigate to the language configuration interface. 2. Add an invalid language parameter (e.g., " englishz"). 3. Click the Save button. | L56: The application should return the user cleanly back to the home language page view. | M56: The application didn't return to the home language page; instead, it got stuck in an infinity load screen. | O56: Open | Q56: Aly | T56: مش فاهمها
C57: System fails to prevent duplicate language creation when using different language names ("arabic" and "العربيه") | D57: AY | F57: Medium | G57: Edge Browser - Windows 10 / 11 - Android 14 | H57: TC_ADMIN_365 | J57: The system allows the creation of duplicate language entries if the language name is entered in a different translation or script (e.g., English text vs. Arabic script), bypassing duplicate-checking constraints. | K57: 1. Navigate to the language configuration page. 2. Click Add and add language "arabic", then click Save. 3. Click Add again to create another language entry. 4. Add the new language name as "العربيه". 5. Click Save. | L57: The system should recognize it as a duplicate language, prevent saving "العربيه", and display a validation message stating "Already exists". | M57: The system fails to recognize the duplicate entry across different language names/scripts, failing to throw the "Already exists" validation error as required. | Q57: Aly
A58: Bug_037 | B58: Nationalities | C58: Special characters in nationality names cause UI layout issues | D58: Afram | E58: US_016 | F58: Medium | G58: Edge Browser - Windows 10 / 11 - Android 14 | H58: TC_ADMIN_417 | I58: US_016 | J58: Entering nationality names containing special characters causes unexpected UI behavior and layout issues in the nationality table. | K58: 1. Click Add button 2. Enter nationality name with special characters (@@@###%%%HR_Method!!!) 3. Click Save 4. Observe table and UI behavior | L58: The system should validate input properly and maintain a stable UI layout. | M58: UI remains functional and readable. | N58: Special characters caused UI layout issues in nationality table. | O58: Screenshot / Video if available | P58: Open | Q58: Unassigned | R58: Afram | S58: 46180 | T58: Input validation issue in nationality name field.
A59: Bug_038 | B59: Nationalities | C59: Page refresh during edit corrupts nationality data | D59: Afram | E59: US_016 | F59: High | G59: Edge Browser - Windows 10 / 11 - Android 14 | H59: TC_ADMIN_425 | I59: US_016 | J59: Refreshing the browser while editing a nationality causes corruption of existing data. | K59: 1. Open Edit form for nationality 2. Modify name 3. Do not click Save 4. Refresh browser (F5) 5. Return to table 6. Open record again | L59: Unsaved changes should be discarded safely and original data should remain unchanged. | M59: Nationality data became corrupted after page refresh during edit process. | N59: Screenshot / Video if available | O59: Open | P59: Unassigned | Q59: Afram | R59: 46180 | S59: Unsaved edit state not handled correctly during refresh.
A60: Bug_076 | B60: Admin / Corporate Branding | C60: Color field accepts invalid hex codes without validation error | D60: Omar | F60: High | G60: Edge Browser - Windows 10 / 11 - Android 14 | H60: TC_ADMIN_451 | I60: US_017 | J60: When Admin enters an invalid hex color code (e.g., 'ZZZZZZ') in the Primary Color field on the Corporate Branding page and clicks Publish, the system does not display a validation error message and accepts the invalid value. | K60: 1. Login as Admin 2. Navigate to Admin Corporate Branding 3. Click on Primary Color field 4. Type invalid value 'ZZZZZZ' 5. Click Publish | L60: System should display a validation error message indicating invalid hex code; invalid color should not be applied | M60: No validation error shown; system appears to accept invalid hex code without rejection | O60: Open | P60: Omar | Q60: Omar | S60: Root Cause: Missing input validation for hex color field. Frontend validation rule for hex color format not implemented. | T60: بيقول invalid عادي
A61: Bug_077 | B61: Admin / Corporate Branding | C61: GIF file accepted as company logo without validation error | D61: Omar | F61: Medium | G61: Edge Browser - Windows 10 / 11 - Android 14 | H61: TC_ADMIN_457 | I61: US_017 | J61: When Admin uploads a GIF file as Company Logo on the Corporate Branding page, the system accepts it without displaying a validation error. Based on standard requirements, only specific image formats (PNG, JPG) should be accepted. | K61: 1. Login as Admin 2. Navigate to Admin Corporate Branding 3. Click Upload for Company Logo 4. Select a .gif file 5. Observe behavior | L61: System should display validation error for unsupported GIF file type and reject the upload | M61: GIF file accepted without error message; logo replaced with GIF | O61: Open | P61: Omar | Q61: Omar | S61: Root Cause: File type validation does not include GIF in the list of rejected formats. File type whitelist may be too permissive. | T61: مكتوب انه بيسمح بالـ gif عادي
A62: Bug_078 | B62: Admin / Corporate Branding | C62: Publish button not disabled after first click allowing multiple rapid clicks | D62: Omar | F62: Medium | G62: Edge Browser - Windows 10 / 11 - Android 14 | H62: TC_ADMIN_459 | I62: US_017 | J62: When Admin clicks the Publish button multiple times rapidly on the Corporate Branding page, the button is not disabled after the first click. This could cause duplicate save requests to be sent to the server. | K62: 1. Login as Admin 2. Navigate to Admin Corporate Branding 3. Make valid branding changes 4. Click Publish button rapidly multiple times 5. Observe behavior | L62: Publish button should be disabled after first click to prevent duplicate submissions; only one save request should be processed | M62: Publish button remains enabled after first click; multiple rapid clicks cause multiple save requests | O62: Open | P62: Omar | Q62: Omar | S62: Root Cause: Publish button lacks click debounce or disable-on-click implementation. No frontend protection against double submission. | T62: زرار الـ publish أصلا بيختفي
A63: Bug_079 | B63: Admin / Corporate Branding | C63: Login page does not reflect updated company logo after Admin publishes new branding | D63: Omar | F63: High | G63: Edge Browser - Windows 10 / 11 - Android 14 | I63: US_017 | J63: After Admin publishes a new company logo on the Corporate Branding page, the login page still displays the old/default logo. The branding change is not immediately reflected on the login page even after clearing browser cache. | K63: 1. Login as Admin 2. Navigate to Admin → Corporate Branding 3. Upload a new company logo 4. Click Publish 5. Logout 6. Observe the login page logo | L63: Login page should display the newly published company logo immediately after publish | M63: Login page still shows the old/default logo after publishing new branding; logo change only reflects on internal pages | O63: Open | P63: Omar | Q63: Omar | S63: Root Cause: Login page likely caches the logo URL independently. Branding publish does not invalidate the login page logo cache. The login page rendering may not be using the dynamic branding endpoint. | T63: ده للكلاينت وملهوش علاقة بالـ login والـ login banner بتتغير عادي
A64: Bug_080 | B64: Admin / Corporate Branding | C64: No minimum image dimension validation for uploaded company logos | D64: Omar | F64: Medium | G64: Edge Browser - Windows 10 / 11 - Android 14 | I64: US_017 | J64: When Admin uploads a very small image (e.g., 1x1 pixel PNG) as the company logo on the Corporate Branding page, the system accepts the file and publishes it without any validation error regarding image dimensions. This results in a distorted or invisible logo displayed across the application. | K64: 1. Login as Admin 2. Navigate to Admin Corporate Branding 3. Click Upload for Company Logo 4. Select a 1x1 pixel PNG image 5. Click Publish 6. Navigate to any page and observe logo | L64: System should display a validation error indicating the image dimensions are too small (e.g., minimum 100x50px required) | M64: 1x1 pixel image accepted and published; logo area appears blank/distorted across the application | O64: Open | P64: Omar | Q64: Omar | S64: Root Cause: Image dimension validation is missing from both frontend and backend. Only file type and file size validation exists. Minimum resolution check not implemented.
A65: Bug_081 | B65: Admin / Corporate Branding | C65: No WCAG accessibility contrast ratio warning when selecting very light primary color | D65: Omar | F65: Medium | G65: Edge Browser - Windows 10 / 11 - Android 14 | I65: US_017 | J65: When Admin selects a very light primary color (e.g., #EEEEEE) that would result in poor text contrast and fail WCAG AA accessibility standards, the system does not display any warning. The color is applied without informing the Admin of potential accessibility issues. | K65: 1. Login as Admin 2. Navigate to Admin Corporate Branding 3. Click on Primary Color field 4. Enter a very light color hex value: #EEEEEE 5. Click Publish 6. Observe if any warning is shown | L65: System should display an accessibility warning noting that the selected color may not meet WCAG contrast ratio requirements (minimum 4.5:1 for normal text) | M65: No warning displayed; light color #EEEEEE accepted and applied; resulting in white text on near-white background — extremely poor contrast | O65: Open | P65: Omar | Q65: Omar | S65: Root Cause: No contrast ratio calculation or WCAG validation implemented in the color picker component. System lacks accessibility guardrails for color selection.
A66: Bug_082 | B66: Admin / Corporate Branding | C66: Corporate branding changes not recorded in system audit trail | D66: Omar | F66: Low | G66: Edge Browser - Windows 10 / 11 - Android 14 | I66: US_017 | J66: After Admin publishes branding changes (colors, logos) on the Corporate Branding page, no corresponding entry is created in the system audit trail/logs. This is an audit compliance issue as all administrative configuration changes should be logged. | K66: 1. Login as Admin 2. Navigate to Admin Corporate Branding 3. Change Primary Color and publish 4. Navigate to Admin Audit Trail 5. Search for recent branding change | L66: Audit trail should contain an entry recording: who made the change, what was changed, and when it was changed | M66: No audit trail entry found for branding configuration changes; the activity is not logged anywhere in the system | O66: Open | P66: Omar | Q66: Omar | S66: Root Cause: The branding publish action is not wired to the audit log service. Other administrative actions (user changes, etc.) are logged but branding changes were not included in the audit logging implementation.
A67: Bug_039 | B67: Email Configuration | C67: Authentication section disappears after page refresh | D67: Afram | E67: US_018 | F67: High | G67: Edge Browser - Windows 10 / 11 - Android 14 | H67: TC_NAT_003 | I67: US_018 | J67: Authentication section is not retained after refreshing the Email Configuration page. | K67: 1. Navigate to Email Configuration page 2. Verify Authentication section visible 3. Refresh browser (F5) 4. Observe section | L67: Authentication section should remain visible after refresh and page should maintain its state. | M67: Authentication section disappeared after refresh. | N67: Screenshot / Video if available | O67: Open | P67: Unassigned | Q67: Afram | R67: 46180 | S67: UI state is not persisted correctly after refresh.
A68: Bug_040 | B68: Email Configuration | C68: Navigation menu items remain collapsed after returning to desktop view | D68: Afram | E68: US_018 | F68: Medium | G68: Edge Browser - Windows 10 / 11 - Android 14 | H68: TC_NAT_004 | I68: US_018 | J68: Navigation items stay hidden inside “More” menu after resizing browser back to desktop resolution. | K68: 1. Open page in desktop resolution 2. Resize to mobile view 3. Verify “More” menu 4. Resize back to desktop 5. Observe navigation | L68: Hidden menu items should re-expand and display normally in desktop view. | M68: Menu items remained inside “More” button after returning to desktop view. | N68: Screenshot / Video if available | O68: Open | P68: Unassigned | Q68: Afram | R68: 46180 | S68: Responsive layout does not reset correctly after viewport change.
A69: Bug_041 | B69: Email Configuration | C69: Conflicting success and failure messages displayed during SMTP save and test email failure | D69: Afram | E69: US_018 | F69: High | G69: Edge Browser - Windows 10 / 11 - Android 14 | H69: TC_SMTP_001 | I69: US_018 | J69: The system shows contradictory messages when SMTP configuration save succeeds but test email sending fails. | K69: 1. Enter SMTP configuration details 2. Click Save 3. Observe system messages | L69: System should clearly separate configuration save status from test email sending result without showing misleading success state. | M69: System displayed both “Failed – Test Email Not Sent” and “Success – Successfully Saved” simultaneously. | N69: Screenshot / Video if available | O69: Open | P69: Unassigned | Q69: Afram | R69: 46180 | S69: Messaging logic is not properly separated between save operation and test email result.
A70: Bug_042 | B70: Email Configuration | C70: SMTP Host accepts invalid format and allows saving | D70: Afram | E70: US_018 | F70: High | G70: Edge Browser - Windows 10 / 11 - Android 14 | H70: TC_SMTP_002 | I70: US_018 | J70: Invalid SMTP host formats are accepted and saved without validation. | K70: 1. Enter invalid SMTP Host (@@@smtp###) 2. Click Save | L70: The system should validate SMTP host format and block saving for invalid inputs. | M70: Invalid host was successfully saved. | N70: Screenshot / Video if available | O70: Open | P70: Unassigned | Q70: Afram | R70: 46180 | S70: SMTP host validation is missing or incorrectly implemented.
A71: Bug_043 | B71: Email Configuration | C71: System allows saving configuration with empty SMTP Port | D71: Afram | E71: US_018 | F71: Critical | G71: Edge Browser - Windows 10 / 11 - Android 14 | H71: TC_SMTP_003 | I71: US_018 | J71: The system saves SMTP configuration even when required SMTP Port field is empty. | K71: 1. Enter valid SMTP Host 2. Enter authentication details 3. Leave SMTP Port empty 4. Click Save | L71: System should block saving and display validation error for empty SMTP Port. | M71: Configuration saved successfully with empty SMTP Port. | N71: Screenshot / Video if available | O71: Open | P71: Unassigned | Q71: Afram | R71: 46180 | S71: Missing required field validation for SMTP Port.
A72: Bug_044 | B72: Email Configuration | C72: SMTP Host validation issue duplicated entry (duplicate test case issue resolved) | D72: Afram | E72: US_018 | F72: High | G72: Edge Browser - Windows 10 / 11 - Android 14 | H72: TC_SMTP_004 | I72: US_018 | J72: Repeated SMTP Host validation test case showing same behavior as earlier case but still failing validation. | K72: 1. Enter invalid SMTP Host (@@@smtp###) 2. Click Save | L72: Invalid host should be rejected and not saved. | M72: Invalid host was still accepted and saved. | N72: Screenshot / Video if available | O72: Open | P72: Unassigned | Q72: Afram | R72: 46180 | S72: Duplicate validation issue observed in SMTP host field handling.
A73: Bug_045 | B73: Email Configuration | C73: Test email sending causes system freeze and failure | D73: Afram | E73: US_018 | F73: Critical | G73: Edge Browser - Windows 10 / 11 - Android 14 | H73: TC_SMTP_005 | I73: US_018 | J73: Sending test email causes system to hang, and email is not delivered successfully. | K73: 1. Click Send Test Email 2. Enter valid recipient email 3. Click Send 4. Observe system | L73: System should send test email successfully and return confirmation without freezing. | M73: System remained loading, email not sent, and UI became unresponsive/laggy. | N73: Screenshot / Video if available | O73: Open | P73: Unassigned | Q73: Afram | R73: 46180 | S73: Performance or backend SMTP handling issue causing UI freeze during email send.
A74: Bug_046 | B74: Email Configuration | C74: Send Test Email dialog does not close after successful send | D74: Afram | E74: US_018 | F74: Medium | G74: Edge Browser - Windows 10 / 11 - Android 14 | H74: TC_EML_001 | I74: US_018 | J74: The Send Test Email dialog remains open after a successful email send instead of closing automatically. | K74: 1. Enter valid recipient email (test@example.com) 2. Click Send 3. Observe dialog state | L74: Dialog should close automatically after successful email sending and return user to Email Configuration page. | M74: Dialog remained open after successful send. | N74: Screenshot / Video if available | O74: Open | P74: Unassigned | Q74: Afram | R74: 46180 | S74: UI flow does not handle dialog closure after success event.
A75: Bug_047 | B75: Email Configuration | C75: Test email shows failure despite valid recipient email | D75: Afram | E75: US_018 | F75: Critical | G75: Edge Browser - Windows 10 / 11 - Android 14 | H75: TC_EML_002 | I75: US_018 | J75: The system incorrectly reports test email failure even when a valid recipient email is provided. | K75: 1. Enter valid SMTP configuration 2. Enter recipient email (test@example.com) 3. Click Send | L75: System should successfully send email and display confirmation message. | M75: System displayed “Failed – Test Email Not Sent” despite valid email input. | N75: Screenshot / Video if available | O75: Open | P75: Unassigned | Q75: Afram | R75: 46180 | S75: Incorrect email delivery status handling or backend failure.
A76: Bug_048 | B76: Email Configuration | C76: System allows duplicate save operations for same SMTP configuration | D76: Afram | E76: US_018 | F76: Medium | G76: Edge Browser - Windows 10 / 11 - Android 14 | H76: TC_EML_003 | I76: US_018 | J76: Repeated Save clicks create duplicate SMTP configuration entries instead of preventing duplication. | K76: 1. Enter SMTP configuration 2. Click Save 3. Click Save again with same data | L76: System should prevent duplicate configuration or notify user that it already exists. | M76: System accepted repeated save operation normally. | N76: Screenshot / Video if available | O76: Open | P76: Unassigned | Q76: Afram | R76: 46180 | S76: Missing duplicate prevention on Save action.
A77: Bug_049 | B77: Email Configuration | C77: Send Test Email dialog does not retain recipient data after refresh | D77: Afram | E77: US_018 | F77: Medium | G77: Edge Browser - Windows 10 / 11 - Android 14 | H77: TC_EML_004 | I77: US_018 | J77: Refreshing browser while Send Test Email dialog is open clears entered recipient email without warning. | K77: 1. Open Send Test Email dialog 2. Enter recipient email 3. Refresh browser 4. Reopen dialog | L77: System should warn user before losing data or preserve entered recipient email. | M77: Dialog closed and entered email was cleared after refresh. | N77: Screenshot / Video if available | O77: Open | P77: Unassigned | Q77: Afram | R77: 46180 | S77: No state persistence or unsaved data warning implemented.
A78: Bug_050 | B78: Email Configuration | C78: System misbehaves when sending test email to invalid or non-existent mailbox | D78: Afram | E78: US_018 | F78: Medium | G78: Edge Browser - Windows 10 / 11 - Android 14 | H78: TC_EML_005 | I78: US_018 | J78: The system does not handle delivery failure properly and causes UI freeze when sending test email to non-existent mailbox. | K78: 1. Enter recipient email (admin@example.com) 2. Click Send 3. Observe response | L78: System should handle delivery failure gracefully and show appropriate error message without freezing. | M78: System showed success/failure inconsistently and UI froze with infinite loading. | N78: Screenshot / Video if available | O78: Open | P78: Unassigned | Q78: Afram | R78: 46180 | S78: Backend email delivery error handling and UI state management issue.
... A90: Bug_062 | B90: OAuth Configuration | C90: Invalid Redirect URI format is accepted and saved | D90: AY | E90: US_024 | F90: High | G90: Edge Browser - Windows 10 / 11 - Android 14 | H90: TC_OAUTH_004 | I90: US_024 | J90: The system allows saving an invalid Redirect URI without proper validation. | K90: 1. Enter Name: TestingClient 2. Enter Redirect URI: invalid_url_string_example 3. Click Save | L90: The system should reject invalid URL formats and show validation message "Invalid URL" or "Please enter a valid URI format". | M90: The invalid URL was successfully saved without validation error. | N90: Screenshot / Video if available | O90: Open | P90: Unassigned | Q90: AY | R90: 46180 | S90: Missing or broken URL validation for Redirect URI field in OAuth configuration.
A91: Bug_083 | B91: Admin / Language Packages | C91: No warning shown when attempting to install duplicate language package | D91: Omar | F91: High | G91: Edge Browser - Windows 10 / 11 - Android 14 | I91: US_021 | J91: When Admin attempts to install a language package that is already installed, the system does not display a warning or error message indicating that the package is already installed. This may lead to confusion or unexpected behavior. | K91: 1. Login as Admin 2. Navigate to Admin Configuration Language Packages 3. Note an already-installed language package 4. Attempt to install the same package again 5. Observe result | L91: System should display a warning message such as 'This language package is already installed' and prevent duplicate installation | M91: No warning message displayed; system proceeds without informing Admin of duplicate installation attempt | O91: Open | P91: Omar | Q91: Omar | S91: Root Cause: No duplicate check implemented in the language package installation workflow. Backend does not validate if package already exists before proceeding with installation.
A92: Bug_084 | B92: Admin / Language Packages | C92: Language packages list not sorted alphabetically by default | D92: Omar | F92: Low | G92: Edge Browser - Windows 10 / 11 - Android 14 | I92: US_021 | J92: The Language Packages list on the Language Packages page is displayed in the order packages were installed, not in alphabetical order. This makes it difficult to find specific packages when many are installed, especially without a search function. | K92: 1. Login as Admin 2. Install multiple language packages in non-alphabetical order (e.g., Spanish, Arabic, French) 3. Navigate to Language Packages page 4. Observe the order of listed packages | L92: Language packages should be listed in alphabetical order by language name by default to improve findability | M92: Language packages are listed in installation order, not alphabetically. For example: Spanish, Arabic, French (installation order) instead of Arabic, French, Spanish (alphabetical) | O92: Open | P92: Omar | Q92: Omar | S92: Root Cause: The database query fetching language packages does not include an ORDER BY clause for language name. Default ordering uses insertion order.
A93: Bug_085 | B93: Admin / Language Packages | C93: RTL layout not fully applied when Arabic language package selected | D93: Omar | F93: High | G93: Edge Browser - Windows 10 / 11 - Android 14 | I93: US_021 | J93: After installing the Arabic language package and switching the UI language to Arabic, the application does not fully implement Right-to-Left (RTL) layout. While text content is translated to Arabic, the UI layout (navigation, form alignment, button placement) remains Left-to-Right (LTR), creating a broken and inconsistent user experience for Arabic-speaking users. | K93: 1. Login as Admin 2. Install Arabic language package 3. Navigate to Profile Display 4. Change language preference to Arabic 5. Observe the entire UI layout | L93: After selecting Arabic, the entire UI should switch to RTL layout: navigation on the right, text right-aligned, form labels on the right side, scroll direction reversed | M93: Only the text content is translated to Arabic; the UI layout remains LTR. Navigation bar stays on the left, forms are left-aligned, and the overall layout is inconsistent for RTL reading patterns | O93: Open | P93: Omar | Q93: Omar | S93: Root Cause: RTL CSS stylesheet (dir='rtl') is not being applied globally when Arabic is selected. The language switching mechanism only updates text translations without toggling the layout direction attribute.
A94: Bug_086 | B94: Admin / Language Packages | C94: Language names not displayed in native script in Language Packages list | D94: Omar | F94: Low | G94: Edge Browser - Windows 10 / 11 - Android 14 | I94: US_021 | J94: The Language Packages list displays language names in English only (e.g., 'Arabic', 'French'). International best practice and user expectation is to also show the language name in its native script (e.g., Arabic: عربي, French: Français, German: Deutsch) to help non-English-speaking admins identify their language. | K94: 1. Login as Admin 2. Navigate to Admin Language Packages 3. Observe the Language Name column | L94: Language names should be displayed in both English and their native script (e.g., 'Arabic / عربي', 'French / Français') | M94: Language names shown in English only; no native script displayed alongside the English name | O94: Open | P94: Omar | Q94: Omar | S94: Root Cause: Language package metadata only stores and displays the English name. Native script name field is not included in the language package registry or the display component.
A95: Bug_087 | B95: Admin / Language Packages | C95: Language package version information not displayed in Language Packages list | D95: Omar | F95: Low | G95: Edge Browser - Windows 10 / 11 - Android 14 | I95: US_021 | J95: The Language Packages list does not display version information for installed language packages. Version information is important for administrators to know if packages are up to date and for troubleshooting translation issues. | K95: 1. Login as Admin 2. Navigate to Admin Language Packages 3. Look for version column or version information for each package | L95: Language package version number should be visible in the packages list or in package details | M95: No version information is shown in the Language Packages list; only package name and status are visible without any version indicator | O95: Open | P95: Omar | Q95: Omar | S95: Root Cause: The Language Packages list view component does not include a version column. Version metadata may exist in the database but is not being rendered in the UI list view.
A96: Bug_088 | B96: Admin / Language Packages | C96: Deleted language package still visible in user preferences dropdown until page refresh | D96: Omar | F96: Medium | G96: Edge Browser - Windows 10 / 11 - Android 14 | I96: US_021 | J96: After Admin deletes a language package from the Language Packages page, the deleted language still appears in the user language preference dropdown on the User Profile/Display page. The deleted language is only removed from the dropdown after the user manually refreshes the page. | K96: 1. Login as Admin 2. Install a non-default language package (e.g., French) 3. Navigate to User Profile Display 4. Verify French appears in language dropdown 5. Navigate back and delete the French language package 6. Navigate back to User Profile Display 7. Observe language dropdown | L96: After deleting a language package, it should immediately be removed from all user language preference dropdowns without requiring a page refresh | M96: The deleted language package (French) still appears in the user language preference dropdown. Only after manually refreshing the page does it disappear from the dropdown | O96: Open | P96: Omar | Q96: Omar | S96: Root Cause: The user preferences dropdown uses cached language data that is not invalidated when a language package is deleted. The cache or state is only refreshed on page load.
A97: Bug_089 | B97: Admin / Modules | C97: No search or filter functionality available on Modules page | D97: Omar | F97: Low | G97: Edge Browser - Windows 10 / 11 - Android 14 | I97: US_022 | J97: The Modules configuration page does not provide any search bar or filter functionality. As the number of OrangeHRM modules grows, administrators need to be able to quickly locate specific modules without scrolling through the entire list. | K97: 1. Login as Admin 2. Navigate to Admin Configuration Modules 3. Look for a search bar or filter option 4. Try to quickly find a specific module (e.g., 'Performance') | L97: A search or filter input should be available on the Modules page to allow Admin to quickly locate specific modules | M97: No search bar or filter option is present on the Modules page. Admin must manually scroll through the entire module list to find a specific module | O97: Open | P97: Omar | Q97: Omar | S97: Root Cause: The Modules page UI was not designed with a search component. As it's a relatively short list currently, search was considered unnecessary, but it should be implemented for better usability as the module list grows.
A98: Bug_090 | B98: Admin / Modules | C98: Module enable/disable changes not recorded in system audit trail | D98: Omar | F98: Medium | G98: Edge Browser - Windows 10 / 11 - Android 14 | I98: US_022 | J98: When Admin enables or disables system modules on the Modules configuration page, no corresponding entry is created in the system audit trail. This is a compliance and governance issue — all administrative configuration changes should be logged with user, timestamp, and action details. | K98: 1. Login as Admin 2. Navigate to Admin Configuration Modules 3. Disable a module (e.g., Performance) 4. Click Save 5. Navigate to Admin Audit Trail 6. Search for recent module configuration changes | L98: Audit trail should record: which module was changed, what the change was (enabled/disabled), who made the change, and when | M98: No audit trail entry found for module enable/disable actions. The Modules configuration page changes are not being logged in the system audit trail | O98: Open | P98: Omar | Q98: Omar | S98: Root Cause: The module configuration save action is not integrated with the audit logging service. Similar to BUG_008, this is a systemic gap where several configuration pages are missing audit trail integration.
A99: Bug_091 | B99: Admin / Modules | C99: No module count summary displayed on Modules page | D99: Omar | F99: Low | G99: Edge Browser - Windows 10 / 11 - Android 14 | I99: US_022 | J99: The Modules configuration page does not display any summary of the total number of modules, how many are currently enabled, or how many are disabled. This summary would help Admins quickly understand the system configuration at a glance. | K99: 1. Login as Admin 2. Navigate to Admin Configuration Modules 3. Look for any count indicator showing total modules, enabled count, or disabled count | L99: Page should display a count summary such as 'Total: 12 modules | Enabled: 10 | Disabled: 2' for quick administrative reference | M99: No count summary or statistics are displayed on the Modules page; only the module list with toggles is shown | O99: Open | P99: Omar | Q99: Omar | S99: Root Cause: Module count summary was not part of the original UI design specification. It is a UX enhancement that was not implemented in the current version.
A100: Bug_092 | B100: Admin / LDAP Configuration | C100: LDAP Server URI field has no maximum character limit enforcement | D100: Omar | F100: Medium | G100: Edge Browser - Windows 10 / 11 - Android 14 | I100: US_025 | J100: The LDAP Server URI input field on the LDAP Configuration page does not enforce a maximum character limit. When an excessively long string (500+ characters) is entered in the Server URI field, the system accepts it without validation. This could cause database issues or application errors. | K100: 1. Login as Admin 2. Navigate to Admin LDAP Configuration 3. Enable LDAP 4. Enter a 600-character string in the Server URI field 5. Click Save | L100: Field should enforce a reasonable maximum character limit (e.g., 255 characters) and display a validation error if exceeded | M100: Server URI field accepts 600+ character input without any validation error or character limit restriction; excessively long value is saved to the database | O100: Open | P100: Omar | Q100: Omar | S100: Root Cause: The Server URI input field is missing the maxlength HTML attribute and corresponding backend validation for maximum length. Database column may also lack proper length constraint.
A101: Bug_093 | B101: Admin / LDAP Configuration | C101: Test Connection button enabled even when required Server URI field is empty | D101: Omar | F101: Medium | G101: Edge Browser - Windows 10 / 11 - Android 14 | I101: US_025 | J101: On the LDAP Configuration page, the 'Test Connection' button remains enabled and clickable even when the required Server URI field is empty. Clicking Test Connection with an empty Server URI results in an unhelpful generic error or unexpected behavior instead of a clear validation message. | K101: 1. Login as Admin 2. Navigate to Admin LDAP Configuration 3. Enable LDAP toggle 4. Leave Server URI field empty 5. Click Test Connection button 6. Observe button state and result | L101: Test Connection button should be disabled/greyed out until at least the Server URI field is filled with a value. If clicked with empty required fields, a clear validation message should appear | M101: Test Connection button is active and clickable with empty Server URI. Clicking it either shows a generic network error or an unhelpful error message without guiding the Admin to fill the required field first | O101: Open | P101: Omar | Q101: Omar | S101: Root Cause: The Test Connection button state is not bound to the validation state of the required Server URI field. No reactive form validation is implemented to disable the button when prerequisites are not met.
A102: Bug_094 | B102: Localization / Languages | C102: Return to language page after editing language does not behave correctly | D102: Aly | E102: US_014 | F102: High | G102: QA Environment | H102: TC_LANG_001 | I102: US_014 | J102: Editing an existing language to a valid parameter does not correctly return user flow to the language page as expected. | K102: 1. Edit existing language to valid parameter (arabic → ar) > 2. Click Save | L102: System should update language successfully and return user to language page with updated data displayed correctly. | M102: User is expected to return to language page after edit operation. | N102: System does not correctly return to language page or update flow behaves unexpectedly after save. | O102: Screenshot / Video if available | P102: Open | Q102: Unassigned | R102: Aly | S102: 46180 | T102: Navigation flow after language edit is not handled correctly or page redirect logic is inconsistent.
A103: Bug_095 | B103: Languages | C103: Duplicate language creation allowed using different language representation | D103: Aly | E103: US_014 | F103: High | G103: QA Environment | H103: TC_LANG_DUP_001 | I103: US_014 | J103: The system allows creation of duplicate language entries using different representations of the same language (e.g., Arabic and العربيه) without proper duplicate validation. | K103: 1. Add language "arabic" > 2. Click Save > 3. Click Add again > 4. Add language "العربيه" > 5. Click Save | L103: System should prevent duplicate language entries regardless of language representation and display message "Already exists". | M103: Second language ("العربيه") was not saved and system should block it with "Already exists" message. | N103: Already exists message expected but data handling is inconsistent or duplicate prevention logic is not robust. | O103: Screenshot / Video if available | P103: Open | Q103: Unassigned | R103: Aly | S103: 46180 | T103: Language uniqueness validation should support multilingual normalization to prevent duplicates.
A104: Bug_096 | B104: Languages | C104: Pagination does not display correct records per page | D104: Aly | E104: US_014 | F104: Medium | G104: QA Environment | H104: TC_LANG_PAG_001 | I104: US_014 | J104: Pagination functionality does not correctly display records when navigating between pages in Languages module. | K104: Click Next/Previous page when language records exceed page size | L104: Each page should display correct and consistent records according to pagination rules | M104: Incorrect records displayed per page | N104: Screenshot / Video if available | O104: Open | P104: Unassigned | Q104: Aly | R104: 46180 | S104: Pagination logic is not correctly mapping dataset to page view.
A105: Bug_097 | B105: Languages | C105: System stuck in infinite loading after submitting invalid language parameter | D105: Aly | E105: US_014 | F105: High | G105: QA Environment | H105: TC_LANG_INV_001 | I105: US_014 | J105: Adding an invalid language parameter causes system to freeze and prevents navigation back to language page. | K105: 1. Add invalid language parameter (englishz) > 2. Click Save | L105: System should validate input and either reject it with error message or return user to language page safely | M105: System gets stuck in infinite loading and does not return to language page | N105: System becomes unresponsive (infinite loading) | O105: Screenshot / Video if available | P105: Open | Q105: Unassigned | R105: Aly | S105: 46180 | T105: Missing validation and error handling causes UI blocking state.
A106: Bug_098 | B106: Organization Info | C106: Page not responsive on iPad Pro - Save button not visible | D106: Aly | E106: US_008 | F106: High | G106: QA Environment | H106: TC_ADMIN_325 | I106: US_008 | J106: General Information page does not properly adapt to different screen sizes, causing UI elements to be hidden on tablet devices. | K106: 1. Open General Information page > 2. Resize browser or open on iPad Pro size > 3. Observe Save button | L106: UI should remain fully responsive and all controls (including Save button) should be visible and accessible on all supported screen sizes. | M106: Save button is not visible on iPad Pro screen size. | N106: Screenshot / Video if available | O106: Open | P106: Unassigned | Q106: Aly Salem | R106: 46180 | S106: Responsive layout issue affecting tablet breakpoint (iPad Pro). ```
A107: Bug_099 | B107: PIM – Add Employee | C107: System allows saving employee with empty Employee ID | D107: Afram | E107: AC 088 | F107: High | G107: Edge Browser - Windows 10 / 11 - Android 14 | H107: TC_PIM_088 | I107: AC 088 | J107: The system allows creation of an employee record without providing an Employee ID, resulting in an employee being saved with a missing identifier. | K107: 1. Navigate to Add Employee page 2. Enter First Name: John 3. Enter Last Name: Doe 4. Leave Employee ID empty 5. Click Save | L107: The system should either prevent submission with a validation message or clearly define Employee ID as optional and auto-generate a unique value. | M107: Employee record is successfully created with an empty Employee ID. | N107: Screenshot / Video if available | O107: Open | P107: Unassigned | Q107: Afram | R107: 46180 | S107: Missing validation or auto-generation logic for Employee ID field.
A108: Bug_100 | B108: PIM – Add Employee | C108: System accepts invalid special characters and numeric values in employee name fields | D108: Afram | E108: AC 090 | F108: High | G108: Edge Browser - Windows 10 / 11 - Android 14 | H108: TC_PIM_090 | I108: AC 090 | J108: The application accepts special characters and numeric values in employee name fields and creates the employee successfully. | K108: 1. Navigate to Add Employee page 2. Enter First Name: @@@### 3. Enter Last Name: 12345 4. Click Save | L108: The system should reject invalid characters and display a validation message. | M108: Employee is created successfully with invalid characters and numeric values in name fields. | N108: Screenshot / Video if available | O108: Open | P108: Unassigned | Q108: Afram | R108: 46180 | S108: Name field validation does not properly restrict unsupported characters or numeric-only names.
A109: Bug_101 | B109: PIM – Add Employee | C109: Leading and trailing spaces are saved in employee name fields | D109: Afram | E109: AC 091 | F109: Medium | G109: Edge Browser - Windows 10 / 11 - Android 14 | H109: TC_PIM_091 | I109: AC 091 | J109: The system stores employee names exactly as entered, including unnecessary leading and trailing spaces. | K109: 1. Navigate to Add Employee page 2. Enter First Name: " John " 3. Enter Last Name: " Doe " 4. Click Save | L109: The system should trim leading and trailing spaces before saving employee data. | M109: Employee data is saved with leading and trailing spaces. | N109: Screenshot / Video if available | O109: Open | P109: Unassigned | Q109: Afram | R109: 46180 | S109: Input sanitization or trimming logic is not applied before persisting employee records.
A110: Bug_102 | B110: PIM – Add Employee | C110: Page refresh during data entry does not provide expected confirmation behavior | D110: Afram | E110: AC 095 | F110: Low | G110: Edge Browser - Windows 10 / 11 - Android 14 | H110: TC_PIM_095 | I110: AC 095 | J110: The system refreshes normally during employee data entry without displaying the expected confirmation behavior defined by the requirement. | K110: 1. Enter employee data 2. Refresh browser page | L110: Page should refresh according to the defined confirmation behavior and allow safe continuation or restart of the process. | M110: Page refreshed normally without the expected confirmation behavior. | N110: Screenshot / Video if available | O110: Open | P110: Unassigned | Q110: Afram | R110: 46180 | S110: Page refresh handling does not align with the specified requirement.
A111: Bug_103 | B111: PIM – Custom Fields | C111: Refreshing page during edit corrupts custom field data | D111: Afram | E111: AC 0173 | F111: High | G111: Edge Browser - Windows 10 / 11 - Android 14 | H111: TC_PIM_0173 | I111: AC 0173 | J111: Refreshing the browser while editing a custom field causes data corruption after reopening the record. | K111: 1. Open Edit Custom Field form 2. Modify field data 3. Refresh browser page before saving 4. Reopen same record | L111: Original data should remain unchanged without corruption or partial updates when refresh occurs before saving. | M111: Record data became corrupted after page refresh during editing. | N111: Screenshot / Video if available | O111: Open | P111: Unassigned | Q111: Afram | R111: 46180 | S111: Unsaved edit state is improperly handled during page refresh, resulting in data corruption.
...

Sheet Test_Summary_Report
A1: TEST EXECUTION SUMMARY REPORT
A2: Date: | B2: 4/25/2026 / 10:34:00 PM
A3: Website: | B3: https://opensource-demo.orangehrmlive.com/web/index.php/auth/login
A4: Testing Environment: | B4: Edge Browser - Windows 10 / 11 - Android / Tablet
A6: User Story
A7: No of user stories | B7: =COUNTA(User_Stories!A:A)-1 -> 80
A8: No of Acceptance Criteria | B8: =COUNTA(User_Stories!C4:C1999) -> 1065
A10: EXECUTION OVERVIEW
A11: Total Test Cases Executed: | B11: =SUM(B12:B13) -> 1462
A12: Test Cases Passed: | B12: =COUNTIF(Test_Cases!L:L, "Passed") -> 1343
A13: Test Cases Failed: | B13: =COUNTIF(Test_Cases!L:L, "Failed") -> 119
A14: Test Cases Blocked: | B14: 0
A16: PASS RATE
A17: Pass Rate: | B17: =(B12/B11) -> 0.91860465
A18: Fail Rate: | B18: =B13/B11 -> 0.081395349
A19: Blocked Rate: | B19: 0
A21: BUG SUMMARY
A22: Critical Issues: | B22: =COUNTIF(Bug_Report!F:F, "Critical") -> 6
A23: High Bugs: | B23: =COUNTIF(Bug_Report!F:F, "High") -> 46
A24: Medium Bugs: | B24: =COUNTIF(Bug_Report!F:F, "Medium") -> 50
A25: Low Bugs: | B25: =COUNTIF(Bug_Report!F:F, "Low") -> 8
A26: Total Bugs Found: | B26: =SUM(B22:B25) -> 110
A28: TEST RESULTS BY CATEGORY
A29: Category | B29: Total | C29: Passed | D29: Pass %
A30: Functional - Age Validation | B30: 9 | C30: 6 | D30: 0.67
A31: Functional - Email Validation | B31: 12 | C31: 12 | D31: 1
A32: Functional - Form Behavior | B32: 6 | C32: 6 | D32: 1
A33: Functional - Name Validation | B33: 14 | C33: 12 | D33: 0.86
A34: Functional - Password Validation | B34: 9 | C34: 9 | D34: 1
A35: Functional - Required Fields | B35: 6 | C35: 6 | D35: 1
A36: RTL Testing - Arabic | B36: 7 | C36: 6 | D36: 0.86
A37: UI/UX - Visual Design | B37: 8 | C37: 7 | D37: 0.88
A38: Uncategorized | B38: 18 | C38: 17 | D38: 0.94
A42: KEY FINDINGS & OBSERVATIONS
A43: Pass Rate: 91.0% - Excellent! Form validation working well
A44: Critical Issue Found: Arabic numerals (١، ٢، ٣) not properly handled in Age field
A45: Network Error Handling: Generic error message instead of specific 'Connection Lost' message
A46: NAME FIELD VALIDATION LOGIC ERROR: Conflicting 50-char and 100-char limits in validation rules
A47: MISSING BUSINESS REQUIREMENTS: Age boundaries (5-120) lack written approval from business
A48: Strong Points: Required fields validation, Email validation, Password matching all working
A49: RTL Support: Arabic text display and alignment mostly working correctly
A50: Form Submission: Double-click prevention and session handling working properly
A51: Improvement Area: Internationalization (i18n) for numeric input formats
A52: UX FLOW INCONSISTENCY: Welcome message doesn't differentiate new registration from login
A55: OVERALL ASSESSMENT
... A60: READY FOR DEPLOYMENT (with minor fixes) Priority Actions: 1. Fix Arabic numeral handling in Age field (implement number normalization) 2. Improve network error messages to be more specific 3. Add unit tests for internationalization scenarios The form is production-ready with high reliability. Address the identified bugs in the next sprint to ensure complete international compliance and better user experience.

Sheet SIQs
A1: SIQ_ID | B1: Req_ID | C1: Requirement | D1: SIQs | E1: Status | F1: Answer
E2: Closed

Sheet Traceability
A1: Req_ID | B1: Linked_TestCases

Sheet Comments
A1: TC_ID | B1: Comments | C1: Status

Sheet Summary_Report
A1: Req_ID | B1: Linked Test Cases | C1: Coverage Status
E4: Total Req's | F4: Covered | G4: Not_Covered | H4: Approved | I4: Rejected | J4: Coverage Percentage
J8: =COUNTIF(Test_Cases!L:L, "Failed") -> 119
